Workbook

Sheet nodes
A1: node_code | B1: ID | C1: voltage | D1: province | E1: node_type | F1: longitude | G1: latitude | H1: elevation | I1: demand_factor | J1: cf_pv | K1: cf_wind
A2: BC_AAL_DSS | B2: 1 | C2: 230 | D2: BC | E2: Distribution | F2: -116.53811 | G2: 49.140156 | H2: 587 | I2: 0.003363 | J2: 0.155703 | K2: 0.06304
A3: BC_ACK_DSS | B3: 2 | C3: 230 | D3: BC | E3: Distribution | F3: -118.99346 | G3: 50.561355 | H3: 514 | I3: 0.003918 | J3: 0.145822 | K3: 0.040198
A4: BC_ALH_GSS | B4: 3 | C4: 230 | D4: BC | E4: Generation | F4: -117.76885 | G4: 49.343024 | H4: 472 | I4: 0.003363 | J4: 0.149954 | K4: 0.035598
A5: BC_ALZ_DSS | B5: 4 | C5: 230 | D5: BC | E5: Distribution | F5: -122.00932 | G5: 49.113555 | H5: 44 | I5: 0.006494 | J5: 0.131906 | K5: 0.071111
A6: BC_ARN_DSS | B6: 5 | C6: 230 | D6: BC | E6: Distribution | F6: -123.04168 | G6: 49.092139 | H6: 3 | I6: 0.015035 | J6: 0.131679 | K6: 0.088419
A7: BC_ASL_GSS | B7: 6 | C7: 230 | D7: BC | E7: Generation | F7: -123.32482 | G7: 49.913835 | H7: 164 | I7: 0.003087 | J7: 0.136098 | K7: 0.033405
A8: BC_ASL_JCT | B8: 7 | C8: 230 | D8: BC | E8: Junction | F8: -123.29228 | G8: 49.915643 | H8: 65 | I8: 0.003087 | J8: 0.135662 | K8: 0.033941
A9: BC_BCR_ISS | B9: 8 | C9: 230 | D9: BC | E9: Industrial | F9: -121.13262 | G9: 55.147518 | H9: 1011 | I9: 0.003341 | J9: 0.126924 | K9: 0.265221
A10: BC_BDH_GSS | B10: 9 | C10: 230 | D10: BC | E10: Generation | F10: -123.40593 | G10: 50.635524 | H10: 564 | I10: 0.003087 | J10: 0.150874 | K10: 0.038106
A11: BC_BDH_JCT | B11: 10 | C11: 230 | D11: BC | E11: Junction | F11: -123.40892 | G11: 50.635395 | H11: 475 | I11: 0.003087 | J11: 0.150851 | K11: 0.038056
A12: BC_BEN_TSS | B12: 11 | C12: 230 | D12: BC | E12: Terminal | F12: -119.53011 | G12: 49.189206 | H12: 331 | I12: 0.003893 | J12: 0.152324 | K12: 0.071497
A13: BC_BLM_DSS | B13: 12 | C13: 230 | D13: BC | E13: Distribution | F13: -121.46842 | G13: 55.139244 | H13: 1127 | I13: 0.003341 | J13: 0.12419 | K13: 0.242821
... A167: BC_WTS_TSS | B167: 166 | C167: 230 | D167: BC | E167: Terminal | F167: -117.73973 | G167: 49.105169 | H167: 580 | I167: 0.002609 | J167: 0.15074 | K167: 0.046364

Sheet exist
A1: ID | B1: Node | C1: province | D1: latitude | E1: longitude | F1: network_node_code | G1: gen_type | H1: unit_installed_capacity | I1: fixed_om_costs | J1: variable_om_costs | K1: emissions | L1: heat_rate | M1: Max_cap | N1: Prod_cost_t1 | O1: Prod_cost_t2 | P1: Prod_cost_t3 | Q1: Prod_cost_t4 | R1: Prod_cost_t5 | S1: Prod_cost_t6
A2: 1 | B2: =VLOOKUP(F2,nodes!$A$1:$L$167,2) -> 26 | C2: BC | D2: 49.493319 | E2: -115.36242 | F2: BC_CBK_DSS | G2: hydro_daily | H2: 8 | I2: =VLOOKUP(G2,gen_cost!$A$1:$AY$31,15) -> 115196 | J2: =VLOOKUP(G2,gen_cost!$A$1:$AY$31,16) -> 5 | K2: =VLOOKUP(G2,gen_cost!$A$1:$AY$31,21) -> 0 | L2: =VLOOKUP(G2,gen_cost!$A$1:$AY$31,22) -> 0 | M2: =H2/100 -> 0.08 | N2: =J2 -> 5 | O2: =+N2 -> 5 | P2: =+O2 -> 5 | Q2: =+P2 -> 5 | R2: =+Q2 -> 5 | S2: =+R2 -> 5
A3: 2 | B3: =VLOOKUP(F3,nodes!$A$1:$L$167,2) -> 26 | C3: BC | D3: 49.493319 | E3: -115.36242 | F3: BC_CBK_DSS | G3: hydro_daily | H3: 8 | I3: =VLOOKUP(G3,gen_cost!$A$1:$AY$31,15) -> 115196 | J3: =VLOOKUP(G3,gen_cost!$A$1:$AY$31,16) -> 5 | K3: =VLOOKUP(G3,gen_cost!$A$1:$AY$31,21) -> 0 | L3: =VLOOKUP(G3,gen_cost!$A$1:$AY$31,22) -> 0 | M3: =H3/100 -> 0.08 | N3: =J3 -> 5 | O3: =+N3 -> 5 | P3: =+O3 -> 5 | Q3: =+P3 -> 5 | R3: =+Q3 -> 5 | S3: =+R3 -> 5
A4: 3 | B4: =VLOOKUP(F4,nodes!$A$1:$L$167,2) -> 26 | C4: BC | D4: 49.493319 | E4: -115.36242 | F4: BC_CBK_DSS | G4: hydro_daily | H4: 8 | I4: =VLOOKUP(G4,gen_cost!$A$1:$AY$31,15) -> 115196 | J4: =VLOOKUP(G4,gen_cost!$A$1:$AY$31,16) -> 5 | K4: =VLOOKUP(G4,gen_cost!$A$1:$AY$31,21) -> 0 | L4: =VLOOKUP(G4,gen_cost!$A$1:$AY$31,22) -> 0 | M4: =H4/100 -> 0.08 | N4: =J4 -> 5 | O4: =+N4 -> 5 | P4: =+O4 -> 5 | Q4: =+P4 -> 5 | R4: =+Q4 -> 5 | S4: =+R4 -> 5
A5: 4 | B5: =VLOOKUP(F5,nodes!$A$1:$L$167,2) -> 3 | C5: BC | D5: 49.343024 | E5: -117.76885 | F5: BC_ALH_GSS | G5: hydro_daily | H5: 92.5 | I5: =VLOOKUP(G5,gen_cost!$A$1:$AY$31,15) -> 115196 | J5: =VLOOKUP(G5,gen_cost!$A$1:$AY$31,16) -> 5 | K5: =VLOOKUP(G5,gen_cost!$A$1:$AY$31,21) -> 0 | L5: =VLOOKUP(G5,gen_cost!$A$1:$AY$31,22) -> 0 | M5: =H5/100 -> 0.925 | N5: =J5 -> 5 | O5: =+N5 -> 5 | P5: =+O5 -> 5 | Q5: =+P5 -> 5 | R5: =+Q5 -> 5 | S5: =+R5 -> 5
A6: 5 | B6: =VLOOKUP(F6,nodes!$A$1:$L$167,2) -> 3 | C6: BC | D6: 49.343024 | E6: -117.76885 | F6: BC_ALH_GSS | G6: hydro_daily | H6: 92.5 | I6: =VLOOKUP(G6,gen_cost!$A$1:$AY$31,15) -> 115196 | J6: =VLOOKUP(G6,gen_cost!$A$1:$AY$31,16) -> 5 | K6: =VLOOKUP(G6,gen_cost!$A$1:$AY$31,21) -> 0 | L6: =VLOOKUP(G6,gen_cost!$A$1:$AY$31,22) -> 0 | M6: =H6/100 -> 0.925 | N6: =J6 -> 5 | O6: =+N6 -> 5 | P6: =+O6 -> 5 | Q6: =+P6 -> 5 | R6: =+Q6 -> 5 | S6: =+R6 -> 5
A7: 6 | B7: =VLOOKUP(F7,nodes!$A$1:$L$167,2) -> 58 | C7: BC | D7: 50.8227 | E7: -118.0295 | F7: BC_ILL_DSS | G7: hydro_run | H7: 10 | I7: =VLOOKUP(G7,gen_cost!$A$1:$AY$31,15) -> 66563 | J7: =VLOOKUP(G7,gen_cost!$A$1:$AY$31,16) -> 1 | K7: =VLOOKUP(G7,gen_cost!$A$1:$AY$31,21) -> 0 | L7: =VLOOKUP(G7,gen_cost!$A$1:$AY$31,22) -> 0 | M7: =H7/100 -> 0.1 | N7: =J7 -> 1 | O7: =+N7 -> 1 | P7: =+O7 -> 1 | Q7: =+P7 -> 1 | R7: =+Q7 -> 1 | S7: =+R7 -> 1
A8: 7 | B8: =VLOOKUP(F8,nodes!$A$1:$L$167,2) -> 27 | C8: BC | D8: 49.371009 | E8: -122.31243 | F8: BC_CBN_DSS | G8: hydro_daily | H8: 9 | I8: =VLOOKUP(G8,gen_cost!$A$1:$AY$31,15) -> 115196 | J8: =VLOOKUP(G8,gen_cost!$A$1:$AY$31,16) -> 5 | K8: =VLOOKUP(G8,gen_cost!$A$1:$AY$31,21) -> 0 | L8: =VLOOKUP(G8,gen_cost!$A$1:$AY$31,22) -> 0 | M8: =H8/100 -> 0.09 | N8: =J8 -> 5 | O8: =+N8 -> 5 | P8: =+O8 -> 5 | Q8: =+P8 -> 5 | R8: =+Q8 -> 5 | S8: =+R8 -> 5
A9: 8 | B9: =VLOOKUP(F9,nodes!$A$1:$L$167,2) -> 38 | C9: BC | D9: 49.373363 | E9: -125.15063 | F9: BC_DMR_DSS | G9: hydro_daily | H9: 28 | I9: =VLOOKUP(G9,gen_cost!$A$1:$AY$31,15) -> 115196 | J9: =VLOOKUP(G9,gen_cost!$A$1:$AY$31,16) -> 5 | K9: =VLOOKUP(G9,gen_cost!$A$1:$AY$31,21) -> 0 | L9: =VLOOKUP(G9,gen_cost!$A$1:$AY$31,22) -> 0 | M9: =H9/100 -> 0.28 | N9: =J9 -> 5 | O9: =+N9 -> 5 | P9: =+O9 -> 5 | Q9: =+P9 -> 5 | R9: =+Q9 -> 5 | S9: =+R9 -> 5
A10: 9 | B10: =VLOOKUP(F10,nodes!$A$1:$L$167,2) -> 6 | C10: BC | D10: 49.914338 | E10: -123.32503 | F10: BC_ASL_GSS | G10: hydro_run | H10: 49.9 | I10: =VLOOKUP(G10,gen_cost!$A$1:$AY$31,15) -> 66563 | J10: =VLOOKUP(G10,gen_cost!$A$1:$AY$31,16) -> 1 | K10: =VLOOKUP(G10,gen_cost!$A$1:$AY$31,21) -> 0 | L10: =VLOOKUP(G10,gen_cost!$A$1:$AY$31,22) -> 0 | M10: =H10/100 -> 0.499 | N10: =J10 -> 1 | O10: =+N10 -> 1 | P10: =+O10 -> 1 | Q10: =+P10 -> 1 | R10: =+Q10 -> 1 | S10: =+R10 -> 1
A11: 10 | B11: =VLOOKUP(F11,nodes!$A$1:$L$167,2) -> 62 | C11: BC | D11: 49.811453 | E11: -121.45849 | F11: BC_KCH_GSS | G11: hydro_run | H11: 9 | I11: =VLOOKUP(G11,gen_cost!$A$1:$AY$31,15) -> 66563 | J11: =VLOOKUP(G11,gen_cost!$A$1:$AY$31,16) -> 1 | K11: =VLOOKUP(G11,gen_cost!$A$1:$AY$31,21) -> 0 | L11: =VLOOKUP(G11,gen_cost!$A$1:$AY$31,22) -> 0 | M11: =H11/100 -> 0.09 | N11: =J11 -> 1 | O11: =+N11 -> 1 | P11: =+O11 -> 1 | Q11: =+P11 -> 1 | R11: =+Q11 -> 1 | S11: =+R11 -> 1
A12: 11 | B12: =VLOOKUP(F12,nodes!$A$1:$L$167,2) -> 9 | C12: BC | D12: 50.635524 | E12: -123.40593 | F12: BC_BDH_GSS | G12: hydro_run | H12: 25.3 | I12: =VLOOKUP(G12,gen_cost!$A$1:$AY$31,15) -> 66563 | J12: =VLOOKUP(G12,gen_cost!$A$1:$AY$31,16) -> 1 | K12: =VLOOKUP(G12,gen_cost!$A$1:$AY$31,21) -> 0 | L12: =VLOOKUP(G12,gen_cost!$A$1:$AY$31,22) -> 0 | M12: =H12/100 -> 0.253 | N12: =J12 -> 1 | O12: =+N12 -> 1 | P12: =+O12 -> 1 | Q12: =+P12 -> 1 | R12: =+Q12 -> 1 | S12: =+R12 -> 1
A13: 12 | B13: =VLOOKUP(F13,nodes!$A$1:$L$167,2) -> 43 | C13: BC | D13: 50.057918 | E13: -123.13129 | F13: BC_FCN_DSS | G13: hydro_run | H13: 7.6 | I13: =VLOOKUP(G13,gen_cost!$A$1:$AY$31,15) -> 66563 | J13: =VLOOKUP(G13,gen_cost!$A$1:$AY$31,16) -> 1 | K13: =VLOOKUP(G13,gen_cost!$A$1:$AY$31,21) -> 0 | L13: =VLOOKUP(G13,gen_cost!$A$1:$AY$31,22) -> 0 | M13: =H13/100 -> 0.076 | N13: =J13 -> 1 | O13: =+N13 -> 1 | P13: =+O13 -> 1 | Q13: =+P13 -> 1 | R13: =+Q13 -> 1 | S13: =+R13 -> 1
... A267: 266 | B267: =VLOOKUP(F267,nodes!$A$1:$L$167,2) -> 46 | C267: BC | D267: 50.053504 | E267: -126.7798 | F267: BC_GLD_DSS | G267: hydro_daily | H267: 7.3 | I267: =VLOOKUP(G267,gen_cost!$A$1:$AY$31,15) -> 115196 | J267: =VLOOKUP(G267,gen_cost!$A$1:$AY$31,16) -> 5 | K267: =VLOOKUP(G267,gen_cost!$A$1:$AY$31,21) -> 0 | L267: =VLOOKUP(G267,gen_cost!$A$1:$AY$31,22) -> 0 | M267: =H267/100 -> 0.073 | N267: =J267 -> 5 | O267: =+N267 -> 5 | P267: =+O267 -> 5 | Q267: =+P267 -> 5 | R267: =+Q267 -> 5 | S267: =+R267 -> 5

Sheet cand
A1: node_code | B1: ID_ref | C1: voltage | D1: province | E1: cf_pv | F1: cf_wind | G1: ID | H1: Node | I1: gen_type | J1: emissions | K1: heat_rate | L1: Prod_cost_t1 | M1: Prod_cost_t2 | N1: Prod_cost_t3 | O1: Prod_cost_t4 | P1: Prod_cost_t5 | Q1: Prod_cost_t6 | R1: Inv_cost_t1 | S1: Inv_cost_t2 | T1: Inv_cost_t3 | U1: Inv_cost_t4 | V1: Inv_cost_t5 | W1: Inv_cost_t6 | X1: Prod_cap | Y1: Q
A2: BC_QTY_GSS | B2: 111 | C2: 230 | D2: BC | E2: 0.12835 | F2: 0.276245 | G2: 32 | H2: =B2 -> 111 | I2: wind_onshore | J2: =VLOOKUP(I2,gen_cost!$A$1:$AY$31,21) -> 0 | K2: =VLOOKUP(I2,gen_cost!$A$1:$AY$31,22) -> 0 | L2: =VLOOKUP(I2,gen_cost!$A$1:$AY$31,16) -> 0 | M2: =+L2 -> 0 | N2: =+M2 -> 0 | O2: =+N2 -> 0 | P2: =+O2 -> 0 | Q2: =+P2 -> 0 | R2: =VLOOKUP(I2,gen_cost!$A$1:$AY$31,14) -> 298.39 | S2: =+R2 -> 298.39 | T2: =+S2 -> 298.39 | U2: =+T2 -> 298.39 | V2: =+U2 -> 298.39 | W2: =+V2 -> 298.39 | X2: 20 | Y2: 10
A3: BC_MRC_ISS | B3: 93 | C3: 230 | D3: BC | E3: 0.128306 | F3: 0.270971 | G3: 33 | H3: =B3 -> 93 | I3: wind_onshore | J3: =VLOOKUP(I3,gen_cost!$A$1:$AY$31,21) -> 0 | K3: =VLOOKUP(I3,gen_cost!$A$1:$AY$31,22) -> 0 | L3: =VLOOKUP(I3,gen_cost!$A$1:$AY$31,16) -> 0 | M3: =+L3 -> 0 | N3: =+M3 -> 0 | O3: =+N3 -> 0 | P3: =+O3 -> 0 | Q3: =+P3 -> 0 | R3: =VLOOKUP(I3,gen_cost!$A$1:$AY$31,14) -> 298.39 | S3: =+R3 -> 298.39 | T3: =+S3 -> 298.39 | U3: =+T3 -> 298.39 | V3: =+U3 -> 298.39 | W3: =+V3 -> 298.39 | X3: 20 | Y3: 10
A4: BC_QNT_DSS | B4: 109 | C4: 230 | D4: BC | E4: 0.128306 | F4: 0.270971 | G4: 55 | H4: =B4 -> 109 | I4: wind_onshore | J4: =VLOOKUP(I4,gen_cost!$A$1:$AY$31,21) -> 0 | K4: =VLOOKUP(I4,gen_cost!$A$1:$AY$31,22) -> 0 | L4: =VLOOKUP(I4,gen_cost!$A$1:$AY$31,16) -> 0 | M4: =+L4 -> 0 | N4: =+M4 -> 0 | O4: =+N4 -> 0 | P4: =+O4 -> 0 | Q4: =+P4 -> 0 | R4: =VLOOKUP(I4,gen_cost!$A$1:$AY$31,14) -> 298.39 | S4: =+R4 -> 298.39 | T4: =+S4 -> 298.39 | U4: =+T4 -> 298.39 | V4: =+U4 -> 298.39 | W4: =+V4 -> 298.39 | X4: 20 | Y4: 10
A5: BC_MRC_JCT | B5: 94 | C5: 230 | D5: BC | E5: 0.12792 | F5: 0.269426 | G5: 63 | H5: =B5 -> 94 | I5: wind_onshore | J5: =VLOOKUP(I5,gen_cost!$A$1:$AY$31,21) -> 0 | K5: =VLOOKUP(I5,gen_cost!$A$1:$AY$31,22) -> 0 | L5: =VLOOKUP(I5,gen_cost!$A$1:$AY$31,16) -> 0 | M5: =+L5 -> 0 | N5: =+M5 -> 0 | O5: =+N5 -> 0 | P5: =+O5 -> 0 | Q5: =+P5 -> 0 | R5: =VLOOKUP(I5,gen_cost!$A$1:$AY$31,14) -> 298.39 | S5: =+R5 -> 298.39 | T5: =+S5 -> 298.39 | U5: =+T5 -> 298.39 | V5: =+U5 -> 298.39 | W5: =+V5 -> 298.39 | X5: 20 | Y5: 10
A6: BC_BCR_ISS | B6: 8 | C6: 230 | D6: BC | E6: 0.126924 | F6: 0.265221 | G6: 65 | H6: =B6 -> 8 | I6: wind_onshore | J6: =VLOOKUP(I6,gen_cost!$A$1:$AY$31,21) -> 0 | K6: =VLOOKUP(I6,gen_cost!$A$1:$AY$31,22) -> 0 | L6: =VLOOKUP(I6,gen_cost!$A$1:$AY$31,16) -> 0 | M6: =+L6 -> 0 | N6: =+M6 -> 0 | O6: =+N6 -> 0 | P6: =+O6 -> 0 | Q6: =+P6 -> 0 | R6: =VLOOKUP(I6,gen_cost!$A$1:$AY$31,14) -> 298.39 | S6: =+R6 -> 298.39 | T6: =+S6 -> 298.39 | U6: =+T6 -> 298.39 | V6: =+U6 -> 298.39 | W6: =+V6 -> 298.39 | X6: 20 | Y6: 10
A7: BC_TLR_DSS | B7: 149 | C7: 230 | D7: BC | E7: 0.126916 | F7: 0.26518 | G7: 66 | H7: =B7 -> 149 | I7: wind_onshore | J7: =VLOOKUP(I7,gen_cost!$A$1:$AY$31,21) -> 0 | K7: =VLOOKUP(I7,gen_cost!$A$1:$AY$31,22) -> 0 | L7: =VLOOKUP(I7,gen_cost!$A$1:$AY$31,16) -> 0 | M7: =+L7 -> 0 | N7: =+M7 -> 0 | O7: =+N7 -> 0 | P7: =+O7 -> 0 | Q7: =+P7 -> 0 | R7: =VLOOKUP(I7,gen_cost!$A$1:$AY$31,14) -> 298.39 | S7: =+R7 -> 298.39 | T7: =+S7 -> 298.39 | U7: =+T7 -> 298.39 | V7: =+U7 -> 298.39 | W7: =+V7 -> 298.39 | X7: 20 | Y7: 10
A8: BC_MLW_GSS | B8: 87 | C8: 230 | D8: BC | E8: 0.126263 | F8: 0.262828 | G8: 67 | H8: =B8 -> 87 | I8: wind_onshore | J8: =VLOOKUP(I8,gen_cost!$A$1:$AY$31,21) -> 0 | K8: =VLOOKUP(I8,gen_cost!$A$1:$AY$31,22) -> 0 | L8: =VLOOKUP(I8,gen_cost!$A$1:$AY$31,16) -> 0 | M8: =+L8 -> 0 | N8: =+M8 -> 0 | O8: =+N8 -> 0 | P8: =+O8 -> 0 | Q8: =+P8 -> 0 | R8: =VLOOKUP(I8,gen_cost!$A$1:$AY$31,14) -> 298.39 | S8: =+R8 -> 298.39 | T8: =+S8 -> 298.39 | U8: =+T8 -> 298.39 | V8: =+U8 -> 298.39 | W8: =+V8 -> 298.39 | X8: 20 | Y8: 10
A9: BC_MLW_JCT | B9: 88 | C9: 230 | D9: BC | E9: 0.125268 | F9: 0.256032 | G9: 68 | H9: =B9 -> 88 | I9: wind_onshore | J9: =VLOOKUP(I9,gen_cost!$A$1:$AY$31,21) -> 0 | K9: =VLOOKUP(I9,gen_cost!$A$1:$AY$31,22) -> 0 | L9: =VLOOKUP(I9,gen_cost!$A$1:$AY$31,16) -> 0 | M9: =+L9 -> 0 | N9: =+M9 -> 0 | O9: =+N9 -> 0 | P9: =+O9 -> 0 | Q9: =+P9 -> 0 | R9: =VLOOKUP(I9,gen_cost!$A$1:$AY$31,14) -> 298.39 | S9: =+R9 -> 298.39 | T9: =+S9 -> 298.39 | U9: =+T9 -> 298.39 | V9: =+U9 -> 298.39 | W9: =+V9 -> 298.39 | X9: 20 | Y9: 10
A10: BC_MNK_JCT | B10: 91 | C10: 230 | D10: BC | E10: 0.123835 | F10: 0.255795 | G10: 32 | H10: 2 | I10: solar_PV | J10: =VLOOKUP(I10,gen_cost!$A$1:$AY$31,21) -> 0 | K10: =VLOOKUP(I10,gen_cost!$A$1:$AY$31,22) -> 0 | L10: =VLOOKUP(I10,gen_cost!$A$1:$AY$31,16) -> 0 | M10: =+L10 -> 0 | N10: =+M10 -> 0 | O10: =+N10 -> 0 | P10: =+O10 -> 0 | Q10: =+P10 -> 0 | R10: =VLOOKUP(I10,gen_cost!$A$1:$AY$31,14) -> 201.62 | S10: =+R10 -> 201.62 | T10: =+S10 -> 201.62 | U10: =+T10 -> 201.62 | V10: =+U10 -> 201.62 | W10: =+V10 -> 201.62 | X10: 20 | Y10: 10
A11: BC_SNK_DSS | B11: 133 | C11: 230 | D11: BC | E11: 0.123834 | F11: 0.255664 | G11: 33 | H11: 3 | I11: solar_PV | J11: =VLOOKUP(I11,gen_cost!$A$1:$AY$31,21) -> 0 | K11: =VLOOKUP(I11,gen_cost!$A$1:$AY$31,22) -> 0 | L11: =VLOOKUP(I11,gen_cost!$A$1:$AY$31,16) -> 0 | M11: =+L11 -> 0 | N11: =+M11 -> 0 | O11: =+N11 -> 0 | P11: =+O11 -> 0 | Q11: =+P11 -> 0 | R11: =VLOOKUP(I11,gen_cost!$A$1:$AY$31,14) -> 201.62 | S11: =+R11 -> 201.62 | T11: =+S11 -> 201.62 | U11: =+T11 -> 201.62 | V11: =+U11 -> 201.62 | W11: =+V11 -> 201.62 | X11: 20 | Y11: 10
A12: BC_KGP_JCT | B12: 65 | C12: 230 | D12: BC | E12: 0.123819 | F12: 0.255626 | G12: 55 | H12: 32 | I12: solar_PV | J12: =VLOOKUP(I12,gen_cost!$A$1:$AY$31,21) -> 0 | K12: =VLOOKUP(I12,gen_cost!$A$1:$AY$31,22) -> 0 | L12: =VLOOKUP(I12,gen_cost!$A$1:$AY$31,16) -> 0 | M12: =+L12 -> 0 | N12: =+M12 -> 0 | O12: =+N12 -> 0 | P12: =+O12 -> 0 | Q12: =+P12 -> 0 | R12: =VLOOKUP(I12,gen_cost!$A$1:$AY$31,14) -> 201.62 | S12: =+R12 -> 201.62 | T12: =+S12 -> 201.62 | U12: =+T12 -> 201.62 | V12: =+U12 -> 201.62 | W12: =+V12 -> 201.62 | X12: 20 | Y12: 10
A13: BC_MKT_SWS | B13: 84 | C13: 230 | D13: BC | E13: 0.125032 | F13: 0.254449 | G13: 63 | H13: 31 | I13: solar_PV | J13: =VLOOKUP(I13,gen_cost!$A$1:$AY$31,21) -> 0 | K13: =VLOOKUP(I13,gen_cost!$A$1:$AY$31,22) -> 0 | L13: =VLOOKUP(I13,gen_cost!$A$1:$AY$31,16) -> 0 | M13: =+L13 -> 0 | N13: =+M13 -> 0 | O13: =+N13 -> 0 | P13: =+O13 -> 0 | Q13: =+P13 -> 0 | R13: =VLOOKUP(I13,gen_cost!$A$1:$AY$31,14) -> 201.62 | S13: =+R13 -> 201.62 | T13: =+S13 -> 201.62 | U13: =+T13 -> 201.62 | V13: =+U13 -> 201.62 | W13: =+V13 -> 201.62 | X13: 20 | Y13: 10
A14: BC_MKL_GSS | B14: 83 | C14: 230 | D14: BC | E14: 0.124549 | F14: 0.251084 | G14: 65 | H14: 1 | I14: solar_PV | J14: =VLOOKUP(I14,gen_cost!$A$1:$AY$31,21) -> 0 | K14: =VLOOKUP(I14,gen_cost!$A$1:$AY$31,22) -> 0 | L14: =VLOOKUP(I14,gen_cost!$A$1:$AY$31,16) -> 0 | M14: =+L14 -> 0 | N14: =+M14 -> 0 | O14: =+N14 -> 0 | P14: =+O14 -> 0 | Q14: =+P14 -> 0 | R14: =VLOOKUP(I14,gen_cost!$A$1:$AY$31,14) -> 201.62 | S14: =+R14 -> 201.62 | T14: =+S14 -> 201.62 | U14: =+T14 -> 201.62 | V14: =+U14 -> 201.62 | W14: =+V14 -> 201.62 | X14: 20 | Y14: 10
A15: BC_SLS_DSS | B15: 132 | C15: 230 | D15: BC | E15: 0.125557 | F15: 0.246919 | G15: 66 | H15: 81 | I15: solar_PV | J15: =VLOOKUP(I15,gen_cost!$A$1:$AY$31,21) -> 0 | K15: =VLOOKUP(I15,gen_cost!$A$1:$AY$31,22) -> 0 | L15: =VLOOKUP(I15,gen_cost!$A$1:$AY$31,16) -> 0 | M15: =+L15 -> 0 | N15: =+M15 -> 0 | O15: =+N15 -> 0 | P15: =+O15 -> 0 | Q15: =+P15 -> 0 | R15: =VLOOKUP(I15,gen_cost!$A$1:$AY$31,14) -> 201.62 | S15: =+R15 -> 201.62 | T15: =+S15 -> 201.62 | U15: =+T15 -> 201.62 | V15: =+U15 -> 201.62 | W15: =+V15 -> 201.62 | X15: 20 | Y15: 10
A16: BC_SGB_ISS | B16: 130 | C16: 230 | D16: BC | E16: 0.125944 | F16: 0.245564 | G16: 67 | H16: 46 | I16: solar_PV | J16: =VLOOKUP(I16,gen_cost!$A$1:$AY$31,21) -> 0 | K16: =VLOOKUP(I16,gen_cost!$A$1:$AY$31,22) -> 0 | L16: =VLOOKUP(I16,gen_cost!$A$1:$AY$31,16) -> 0 | M16: =+L16 -> 0 | N16: =+M16 -> 0 | O16: =+N16 -> 0 | P16: =+O16 -> 0 | Q16: =+P16 -> 0 | R16: =VLOOKUP(I16,gen_cost!$A$1:$AY$31,14) -> 201.62 | S16: =+R16 -> 201.62 | T16: =+S16 -> 201.62 | U16: =+T16 -> 201.62 | V16: =+U16 -> 201.62 | W16: =+V16 -> 201.62 | X16: 20 | Y16: 10
A17: BC_BMT_DSS | B17: 14 | C17: 230 | D17: BC | E17: 0.12563 | F17: 0.242943 | G17: 68 | H17: 45 | I17: solar_PV | J17: =VLOOKUP(I17,gen_cost!$A$1:$AY$31,21) -> 0 | K17: =VLOOKUP(I17,gen_cost!$A$1:$AY$31,22) -> 0 | L17: =VLOOKUP(I17,gen_cost!$A$1:$AY$31,16) -> 0 | M17: =+L17 -> 0 | N17: =+M17 -> 0 | O17: =+N17 -> 0 | P17: =+O17 -> 0 | Q17: =+P17 -> 0 | R17: =VLOOKUP(I17,gen_cost!$A$1:$AY$31,14) -> 201.62 | S17: =+R17 -> 201.62 | T17: =+S17 -> 201.62 | U17: =+T17 -> 201.62 | V17: =+U17 -> 201.62 | W17: =+V17 -> 201.62 | X17: 20 | Y17: 10
A18: BC_BLM_DSS | B18: 12 | C18: 230 | D18: BC | E18: 0.12419 | F18: 0.242821 | G18: 32 | H18: 2 | I18: NG_CCS | J18: =VLOOKUP(I18,gen_cost!$A$1:$AY$31,21) -> 0.037998 | K18: =VLOOKUP(I18,gen_cost!$A$1:$AY$31,22) -> 7.16 | L18: =VLOOKUP(I18,gen_cost!$A$1:$AY$31,16) -> 8.54 | M18: =+L18 -> 8.54 | N18: =+M18 -> 8.54 | O18: =+N18 -> 8.54 | P18: =+O18 -> 8.54 | Q18: =+P18 -> 8.54 | R18: =VLOOKUP(I18,gen_cost!$A$1:$AY$31,14) -> 442.87 | S18: =+R18 -> 442.87 | T18: =+S18 -> 442.87 | U18: =+T18 -> 442.87 | V18: =+U18 -> 442.87 | W18: =+V18 -> 442.87 | X18: 20 | Y18: 10
A19: BC_LAP_GSS | B19: 75 | C19: 230 | D19: BC | E19: 0.124004 | F19: 0.238445 | G19: 33 | H19: 3 | I19: NG_CCS | J19: =VLOOKUP(I19,gen_cost!$A$1:$AY$31,21) -> 0.037998 | K19: =VLOOKUP(I19,gen_cost!$A$1:$AY$31,22) -> 7.16 | L19: =VLOOKUP(I19,gen_cost!$A$1:$AY$31,16) -> 8.54 | M19: =+L19 -> 8.54 | N19: =+M19 -> 8.54 | O19: =+N19 -> 8.54 | P19: =+O19 -> 8.54 | Q19: =+P19 -> 8.54 | R19: =VLOOKUP(I19,gen_cost!$A$1:$AY$31,14) -> 442.87 | S19: =+R19 -> 442.87 | T19: =+S19 -> 442.87 | U19: =+T19 -> 442.87 | V19: =+U19 -> 442.87 | W19: =+V19 -> 442.87 | X19: 20 | Y19: 10
A20: BC_MNK_ISS | B20: 90 | C20: 230 | D20: BC | E20: 0.121778 | F20: 0.235469 | G20: 55 | H20: 32 | I20: NG_CCS | J20: =VLOOKUP(I20,gen_cost!$A$1:$AY$31,21) -> 0.037998 | K20: =VLOOKUP(I20,gen_cost!$A$1:$AY$31,22) -> 7.16 | L20: =VLOOKUP(I20,gen_cost!$A$1:$AY$31,16) -> 8.54 | M20: =+L20 -> 8.54 | N20: =+M20 -> 8.54 | O20: =+N20 -> 8.54 | P20: =+O20 -> 8.54 | Q20: =+P20 -> 8.54 | R20: =VLOOKUP(I20,gen_cost!$A$1:$AY$31,14) -> 442.87 | S20: =+R20 -> 442.87 | T20: =+S20 -> 442.87 | U20: =+T20 -> 442.87 | V20: =+U20 -> 442.87 | W20: =+V20 -> 442.87 | X20: 20 | Y20: 10
A21: BC_RUP_DSS | B21: 119 | C21: 287 | D21: BC | E21: 0.102163 | F21: 0.234133 | G21: 63 | H21: 31 | I21: NG_CCS | J21: =VLOOKUP(I21,gen_cost!$A$1:$AY$31,21) -> 0.037998 | K21: =VLOOKUP(I21,gen_cost!$A$1:$AY$31,22) -> 7.16 | L21: =VLOOKUP(I21,gen_cost!$A$1:$AY$31,16) -> 8.54 | M21: =+L21 -> 8.54 | N21: =+M21 -> 8.54 | O21: =+N21 -> 8.54 | P21: =+O21 -> 8.54 | Q21: =+P21 -> 8.54 | R21: =VLOOKUP(I21,gen_cost!$A$1:$AY$31,14) -> 442.87 | S21: =+R21 -> 442.87 | T21: =+S21 -> 442.87 | U21: =+T21 -> 442.87 | V21: =+U21 -> 442.87 | W21: =+V21 -> 442.87 | X21: 20 | Y21: 10
... A33: BC_WSN_DSS | B33: 165 | C33: 230 | D33: BC | E33: 0.127911 | F33: 0.161535 | G33: 68 | H33: 45 | I33: NG_CCS | J33: =VLOOKUP(I33,gen_cost!$A$1:$AY$31,21) -> 0.037998 | K33: =VLOOKUP(I33,gen_cost!$A$1:$AY$31,22) -> 7.16 | L33: =VLOOKUP(I33,gen_cost!$A$1:$AY$31,16) -> 8.54 | M33: =+L33 -> 8.54 | N33: =+M33 -> 8.54 | O33: =+N33 -> 8.54 | P33: =+O33 -> 8.54 | Q33: =+P33 -> 8.54 | R33: =VLOOKUP(I33,gen_cost!$A$1:$AY$31,14) -> 442.87 | S33: =+R33 -> 442.87 | T33: =+S33 -> 442.87 | U33: =+T33 -> 442.87 | V33: =+U33 -> 442.87 | W33: =+V33 -> 442.87 | X33: 20 | Y33: 10
A34: BC_GLN_DSS | B34: 47 | C34: 230 | D34: BC | E34: 0.126067 | F34: 0.158862 | G34: 53 | H34: =B34 -> 47 | I34: wind_onshore | J34: =VLOOKUP(I34,gen_cost!$A$1:$AY$31,21) -> 0 | K34: =VLOOKUP(I34,gen_cost!$A$1:$AY$31,22) -> 0 | L34: =VLOOKUP(I34,gen_cost!$A$1:$AY$31,16) -> 0 | M34: =+L34 -> 0 | N34: =+M34 -> 0 | O34: =+N34 -> 0 | P34: =+O34 -> 0 | Q34: =+P34 -> 0 | R34: =VLOOKUP(I34,gen_cost!$A$1:$AY$31,14) -> 298.39 | S34: =+R34 -> 298.39 | T34: =+S34 -> 298.39 | U34: =+T34 -> 298.39 | V34: =+U34 -> 298.39 | W34: =+V34 -> 298.39 | X34: 20 | Y34: 10
A35: BC_MML_DSS | B35: 89 | C35: 230 | D35: BC | E35: 0.123671 | F35: 0.15585 | G35: 62 | H35: =B35 -> 89 | I35: wind_onshore | J35: =VLOOKUP(I35,gen_cost!$A$1:$AY$31,21) -> 0 | K35: =VLOOKUP(I35,gen_cost!$A$1:$AY$31,22) -> 0 | L35: =VLOOKUP(I35,gen_cost!$A$1:$AY$31,16) -> 0 | M35: =+L35 -> 0 | N35: =+M35 -> 0 | O35: =+N35 -> 0 | P35: =+O35 -> 0 | Q35: =+P35 -> 0 | R35: =VLOOKUP(I35,gen_cost!$A$1:$AY$31,14) -> 298.39 | S35: =+R35 -> 298.39 | T35: =+S35 -> 298.39 | U35: =+T35 -> 298.39 | V35: =+U35 -> 298.39 | W35: =+V35 -> 298.39 | X35: 20 | Y35: 10
A36: BC_SVY_DSS | B36: 140 | C36: 230 | D36: BC | E36: 0.126986 | F36: 0.15582 | G36: 53 | H36: 398 | I36: solar_PV | J36: =VLOOKUP(I36,gen_cost!$A$1:$AY$31,21) -> 0 | K36: =VLOOKUP(I36,gen_cost!$A$1:$AY$31,22) -> 0 | L36: =VLOOKUP(I36,gen_cost!$A$1:$AY$31,16) -> 0 | M36: =+L36 -> 0 | N36: =+M36 -> 0 | O36: =+N36 -> 0 | P36: =+O36 -> 0 | Q36: =+P36 -> 0 | R36: =VLOOKUP(I36,gen_cost!$A$1:$AY$31,14) -> 201.62 | S36: =+R36 -> 201.62 | T36: =+S36 -> 201.62 | U36: =+T36 -> 201.62 | V36: =+U36 -> 201.62 | W36: =+V36 -> 201.62 | X36: 20 | Y36: 10
A37: BC_GTP_DSS | B37: 50 | C37: 230 | D37: BC | E37: 0.137418 | F37: 0.149376 | G37: 62 | H37: 400 | I37: solar_PV | J37: =VLOOKUP(I37,gen_cost!$A$1:$AY$31,21) -> 0 | K37: =VLOOKUP(I37,gen_cost!$A$1:$AY$31,22) -> 0 | L37: =VLOOKUP(I37,gen_cost!$A$1:$AY$31,16) -> 0 | M37: =+L37 -> 0 | N37: =+M37 -> 0 | O37: =+N37 -> 0 | P37: =+O37 -> 0 | Q37: =+P37 -> 0 | R37: =VLOOKUP(I37,gen_cost!$A$1:$AY$31,14) -> 201.62 | S37: =+R37 -> 201.62 | T37: =+S37 -> 201.62 | U37: =+T37 -> 201.62 | V37: =+U37 -> 201.62 | W37: =+V37 -> 201.62 | X37: 20 | Y37: 10
A38: BC_BLW_DSS | B38: 13 | C38: 230 | D38: BC | E38: 0.133289 | F38: 0.149361 | G38: 53 | H38: 398 | I38: NG_CCS | J38: =VLOOKUP(I38,gen_cost!$A$1:$AY$31,21) -> 0.037998 | K38: =VLOOKUP(I38,gen_cost!$A$1:$AY$31,22) -> 7.16 | L38: =VLOOKUP(I38,gen_cost!$A$1:$AY$31,16) -> 8.54 | M38: =+L38 -> 8.54 | N38: =+M38 -> 8.54 | O38: =+N38 -> 8.54 | P38: =+O38 -> 8.54 | Q38: =+P38 -> 8.54 | R38: =VLOOKUP(I38,gen_cost!$A$1:$AY$31,14) -> 442.87 | S38: =+R38 -> 442.87 | T38: =+S38 -> 442.87 | U38: =+T38 -> 442.87 | V38: =+U38 -> 442.87 | W38: =+V38 -> 442.87 | X38: 20 | Y38: 10
A39: BC_QRP_ISS | B39: 110 | C39: 230 | D39: BC | E39: 0.133668 | F39: 0.148623 | G39: 62 | H39: 400 | I39: NG_CCS | J39: =VLOOKUP(I39,gen_cost!$A$1:$AY$31,21) -> 0.037998 | K39: =VLOOKUP(I39,gen_cost!$A$1:$AY$31,22) -> 7.16 | L39: =VLOOKUP(I39,gen_cost!$A$1:$AY$31,16) -> 8.54 | M39: =+L39 -> 8.54 | N39: =+M39 -> 8.54 | O39: =+N39 -> 8.54 | P39: =+O39 -> 8.54 | Q39: =+P39 -> 8.54 | R39: =VLOOKUP(I39,gen_cost!$A$1:$AY$31,14) -> 442.87 | S39: =+R39 -> 442.87 | T39: =+S39 -> 442.87 | U39: =+T39 -> 442.87 | V39: =+U39 -> 442.87 | W39: =+V39 -> 442.87 | X39: 20 | Y39: 10
A40: BC_RBF_DSS | B40: 112 | C40: 230 | D40: BC | E40: 0.133668 | F40: 0.148623 | G40: 53 | H40: 398 | I40: NG_CCS | J40: =VLOOKUP(I40,gen_cost!$A$1:$AY$31,21) -> 0.037998 | K40: =VLOOKUP(I40,gen_cost!$A$1:$AY$31,22) -> 7.16 | L40: =VLOOKUP(I40,gen_cost!$A$1:$AY$31,16) -> 8.54 | M40: =+L40 -> 8.54 | N40: =+M40 -> 8.54 | O40: =+N40 -> 8.54 | P40: =+O40 -> 8.54 | Q40: =+P40 -> 8.54 | R40: =VLOOKUP(I40,gen_cost!$A$1:$AY$31,14) -> 442.87 | S40: =+R40 -> 442.87 | T40: =+S40 -> 442.87 | U40: =+T40 -> 442.87 | V40: =+U40 -> 442.87 | W40: =+V40 -> 442.87 | X40: 20 | Y40: 10
A41: BC_GOW_DSS | B41: 49 | C41: 230 | D41: BC | E41: 0.137082 | F41: 0.148065 | G41: 62 | H41: 400 | I41: NG_CCS | J41: =VLOOKUP(I41,gen_cost!$A$1:$AY$31,21) -> 0.037998 | K41: =VLOOKUP(I41,gen_cost!$A$1:$AY$31,22) -> 7.16 | L41: =VLOOKUP(I41,gen_cost!$A$1:$AY$31,16) -> 8.54 | M41: =+L41 -> 8.54 | N41: =+M41 -> 8.54 | O41: =+N41 -> 8.54 | P41: =+O41 -> 8.54 | Q41: =+P41 -> 8.54 | R41: =VLOOKUP(I41,gen_cost!$A$1:$AY$31,14) -> 442.87 | S41: =+R41 -> 442.87 | T41: =+S41 -> 442.87 | U41: =+T41 -> 442.87 | V41: =+U41 -> 442.87 | W41: =+V41 -> 442.87 | X41: 20 | Y41: 10
A42: BC_PIK_DSS | B42: 107 | C42: 230 | D42: BC | E42: 0.136991 | F42: 0.146435 | G42: 10 | H42: =B42 -> 107 | I42: wind_onshore | J42: =VLOOKUP(I42,gen_cost!$A$1:$AY$31,21) -> 0 | K42: =VLOOKUP(I42,gen_cost!$A$1:$AY$31,22) -> 0 | L42: =VLOOKUP(I42,gen_cost!$A$1:$AY$31,16) -> 0 | M42: =+L42 -> 0 | N42: =+M42 -> 0 | O42: =+N42 -> 0 | P42: =+O42 -> 0 | Q42: =+P42 -> 0 | R42: =VLOOKUP(I42,gen_cost!$A$1:$AY$31,14) -> 298.39 | S42: =+R42 -> 298.39 | T42: =+S42 -> 298.39 | U42: =+T42 -> 298.39 | V42: =+U42 -> 298.39 | W42: =+V42 -> 298.39 | X42: 20 | Y42: 10
A43: BC_SCK_DSS | B43: 127 | C43: 230 | D43: BC | E43: 0.137213 | F43: 0.146255 | G43: 11 | H43: =B43 -> 127 | I43: wind_onshore | J43: =VLOOKUP(I43,gen_cost!$A$1:$AY$31,21) -> 0 | K43: =VLOOKUP(I43,gen_cost!$A$1:$AY$31,22) -> 0 | L43: =VLOOKUP(I43,gen_cost!$A$1:$AY$31,16) -> 0 | M43: =+L43 -> 0 | N43: =+M43 -> 0 | O43: =+N43 -> 0 | P43: =+O43 -> 0 | Q43: =+P43 -> 0 | R43: =VLOOKUP(I43,gen_cost!$A$1:$AY$31,14) -> 298.39 | S43: =+R43 -> 298.39 | T43: =+S43 -> 298.39 | U43: =+T43 -> 298.39 | V43: =+U43 -> 298.39 | W43: =+V43 -> 298.39 | X43: 20 | Y43: 10
A44: BC_HSY_DSS | B44: 55 | C44: 230 | D44: BC | E44: 0.137729 | F44: 0.146134 | G44: 17 | H44: =B44 -> 55 | I44: wind_onshore | J44: =VLOOKUP(I44,gen_cost!$A$1:$AY$31,21) -> 0 | K44: =VLOOKUP(I44,gen_cost!$A$1:$AY$31,22) -> 0 | L44: =VLOOKUP(I44,gen_cost!$A$1:$AY$31,16) -> 0 | M44: =+L44 -> 0 | N44: =+M44 -> 0 | O44: =+N44 -> 0 | P44: =+O44 -> 0 | Q44: =+P44 -> 0 | R44: =VLOOKUP(I44,gen_cost!$A$1:$AY$31,14) -> 298.39 | S44: =+R44 -> 298.39 | T44: =+S44 -> 298.39 | U44: =+T44 -> 298.39 | V44: =+U44 -> 298.39 | W44: =+V44 -> 298.39 | X44: 20 | Y44: 10
A45: BC_ESQ_DSS | B45: 40 | C45: 230 | D45: BC | E45: 0.137296 | F45: 0.144657 | G45: 54 | H45: =B45 -> 40 | I45: wind_onshore | J45: =VLOOKUP(I45,gen_cost!$A$1:$AY$31,21) -> 0 | K45: =VLOOKUP(I45,gen_cost!$A$1:$AY$31,22) -> 0 | L45: =VLOOKUP(I45,gen_cost!$A$1:$AY$31,16) -> 0 | M45: =+L45 -> 0 | N45: =+M45 -> 0 | O45: =+N45 -> 0 | P45: =+O45 -> 0 | Q45: =+P45 -> 0 | R45: =VLOOKUP(I45,gen_cost!$A$1:$AY$31,14) -> 298.39 | S45: =+R45 -> 298.39 | T45: =+S45 -> 298.39 | U45: =+T45 -> 298.39 | V45: =+U45 -> 298.39 | W45: =+V45 -> 298.39 | X45: 20 | Y45: 10
A46: BC_BNT_DSS | B46: 16 | C46: 230 | D46: BC | E46: 0.137296 | F46: 0.144656 | G46: 56 | H46: =B46 -> 16 | I46: wind_onshore | J46: =VLOOKUP(I46,gen_cost!$A$1:$AY$31,21) -> 0 | K46: =VLOOKUP(I46,gen_cost!$A$1:$AY$31,22) -> 0 | L46: =VLOOKUP(I46,gen_cost!$A$1:$AY$31,16) -> 0 | M46: =+L46 -> 0 | N46: =+M46 -> 0 | O46: =+N46 -> 0 | P46: =+O46 -> 0 | Q46: =+P46 -> 0 | R46: =VLOOKUP(I46,gen_cost!$A$1:$AY$31,14) -> 298.39 | S46: =+R46 -> 298.39 | T46: =+S46 -> 298.39 | U46: =+T46 -> 298.39 | V46: =+U46 -> 298.39 | W46: =+V46 -> 298.39 | X46: 20 | Y46: 10
A47: BC_KTG_DSS | B47: 74 | C47: 230 | D47: BC | E47: 0.136505 | F47: 0.140992 | G47: 10 | H47: 443 | I47: solar_PV | J47: =VLOOKUP(I47,gen_cost!$A$1:$AY$31,21) -> 0 | K47: =VLOOKUP(I47,gen_cost!$A$1:$AY$31,22) -> 0 | L47: =VLOOKUP(I47,gen_cost!$A$1:$AY$31,16) -> 0 | M47: =+L47 -> 0 | N47: =+M47 -> 0 | O47: =+N47 -> 0 | P47: =+O47 -> 0 | Q47: =+P47 -> 0 | R47: =VLOOKUP(I47,gen_cost!$A$1:$AY$31,14) -> 201.62 | S47: =+R47 -> 201.62 | T47: =+S47 -> 201.62 | U47: =+T47 -> 201.62 | V47: =+U47 -> 201.62 | W47: =+V47 -> 201.62 | X47: 20 | Y47: 10
A48: BC_GLD_DSS | B48: 46 | C48: 230 | D48: BC | E48: 0.127067 | F48: 0.139251 | G48: 11 | H48: 439 | I48: solar_PV | J48: =VLOOKUP(I48,gen_cost!$A$1:$AY$31,21) -> 0 | K48: =VLOOKUP(I48,gen_cost!$A$1:$AY$31,22) -> 0 | L48: =VLOOKUP(I48,gen_cost!$A$1:$AY$31,16) -> 0 | M48: =+L48 -> 0 | N48: =+M48 -> 0 | O48: =+N48 -> 0 | P48: =+O48 -> 0 | Q48: =+P48 -> 0 | R48: =VLOOKUP(I48,gen_cost!$A$1:$AY$31,14) -> 201.62 | S48: =+R48 -> 201.62 | T48: =+S48 -> 201.62 | U48: =+T48 -> 201.62 | V48: =+U48 -> 201.62 | W48: =+V48 -> 201.62 | X48: 20 | Y48: 10
A49: BC_NTL_DSS | B49: 103 | C49: 138 | D49: BC | E49: 0.161794 | F49: 0.134662 | G49: 17 | H49: 445 | I49: solar_PV | J49: =VLOOKUP(I49,gen_cost!$A$1:$AY$31,21) -> 0 | K49: =VLOOKUP(I49,gen_cost!$A$1:$AY$31,22) -> 0 | L49: =VLOOKUP(I49,gen_cost!$A$1:$AY$31,16) -> 0 | M49: =+L49 -> 0 | N49: =+M49 -> 0 | O49: =+N49 -> 0 | P49: =+O49 -> 0 | Q49: =+P49 -> 0 | R49: =VLOOKUP(I49,gen_cost!$A$1:$AY$31,14) -> 201.62 | S49: =+R49 -> 201.62 | T49: =+S49 -> 201.62 | U49: =+T49 -> 201.62 | V49: =+U49 -> 201.62 | W49: =+V49 -> 201.62 | X49: 20 | Y49: 10
A50: BC_NIC_TSS | B50: 101 | C50: 230 | D50: BC | E50: 0.143589 | F50: 0.132285 | G50: 54 | H50: 453 | I50: solar_PV | J50: =VLOOKUP(I50,gen_cost!$A$1:$AY$31,21) -> 0 | K50: =VLOOKUP(I50,gen_cost!$A$1:$AY$31,22) -> 0 | L50: =VLOOKUP(I50,gen_cost!$A$1:$AY$31,16) -> 0 | M50: =+L50 -> 0 | N50: =+M50 -> 0 | O50: =+N50 -> 0 | P50: =+O50 -> 0 | Q50: =+P50 -> 0 | R50: =VLOOKUP(I50,gen_cost!$A$1:$AY$31,14) -> 201.62 | S50: =+R50 -> 201.62 | T50: =+S50 -> 201.62 | U50: =+T50 -> 201.62 | V50: =+U50 -> 201.62 | W50: =+V50 -> 201.62 | X50: 20 | Y50: 10
A51: BC_TKW_DSS | B51: 148 | C51: 500 | D51: BC | E51: 0.128744 | F51: 0.122983 | G51: 56 | H51: 438 | I51: solar_PV | J51: =VLOOKUP(I51,gen_cost!$A$1:$AY$31,21) -> 0 | K51: =VLOOKUP(I51,gen_cost!$A$1:$AY$31,22) -> 0 | L51: =VLOOKUP(I51,gen_cost!$A$1:$AY$31,16) -> 0 | M51: =+L51 -> 0 | N51: =+M51 -> 0 | O51: =+N51 -> 0 | P51: =+O51 -> 0 | Q51: =+P51 -> 0 | R51: =VLOOKUP(I51,gen_cost!$A$1:$AY$31,14) -> 201.62 | S51: =+R51 -> 201.62 | T51: =+S51 -> 201.62 | U51: =+T51 -> 201.62 | V51: =+U51 -> 201.62 | W51: =+V51 -> 201.62 | X51: 20 | Y51: 10
A52: BC_RDC_ISS | B52: 115 | C52: 287 | D52: BC | E52: 0.124704 | F52: 0.121346 | G52: 10 | H52: 443 | I52: NG_CCS | J52: =VLOOKUP(I52,gen_cost!$A$1:$AY$31,21) -> 0.037998 | K52: =VLOOKUP(I52,gen_cost!$A$1:$AY$31,22) -> 7.16 | L52: =VLOOKUP(I52,gen_cost!$A$1:$AY$31,16) -> 8.54 | M52: =+L52 -> 8.54 | N52: =+M52 -> 8.54 | O52: =+N52 -> 8.54 | P52: =+O52 -> 8.54 | Q52: =+P52 -> 8.54 | R52: =VLOOKUP(I52,gen_cost!$A$1:$AY$31,14) -> 442.87 | S52: =+R52 -> 442.87 | T52: =+S52 -> 442.87 | U52: =+T52 -> 442.87 | V52: =+U52 -> 442.87 | W52: =+V52 -> 442.87 | X52: 20 | Y52: 10
A53: BC_SAT_DSS | B53: 124 | C53: 230 | D53: BC | E53: 0.134632 | F53: 0.121004 | G53: 11 | H53: 439 | I53: NG_CCS | J53: =VLOOKUP(I53,gen_cost!$A$1:$AY$31,21) -> 0.037998 | K53: =VLOOKUP(I53,gen_cost!$A$1:$AY$31,22) -> 7.16 | L53: =VLOOKUP(I53,gen_cost!$A$1:$AY$31,16) -> 8.54 | M53: =+L53 -> 8.54 | N53: =+M53 -> 8.54 | O53: =+N53 -> 8.54 | P53: =+O53 -> 8.54 | Q53: =+P53 -> 8.54 | R53: =VLOOKUP(I53,gen_cost!$A$1:$AY$31,14) -> 442.87 | S53: =+R53 -> 442.87 | T53: =+S53 -> 442.87 | U53: =+T53 -> 442.87 | V53: =+U53 -> 442.87 | W53: =+V53 -> 442.87 | X53: 20 | Y53: 10
A54: BC_TAT_DSS | B54: 144 | C54: 287 | D54: BC | E54: 0.125693 | F54: 0.120646 | G54: 17 | H54: 445 | I54: NG_CCS | J54: =VLOOKUP(I54,gen_cost!$A$1:$AY$31,21) -> 0.037998 | K54: =VLOOKUP(I54,gen_cost!$A$1:$AY$31,22) -> 7.16 | L54: =VLOOKUP(I54,gen_cost!$A$1:$AY$31,16) -> 8.54 | M54: =+L54 -> 8.54 | N54: =+M54 -> 8.54 | O54: =+N54 -> 8.54 | P54: =+O54 -> 8.54 | Q54: =+P54 -> 8.54 | R54: =VLOOKUP(I54,gen_cost!$A$1:$AY$31,14) -> 442.87 | S54: =+R54 -> 442.87 | T54: =+S54 -> 442.87 | U54: =+T54 -> 442.87 | V54: =+U54 -> 442.87 | W54: =+V54 -> 442.87 | X54: 20 | Y54: 10
A55: BC_VIT_TSS | B55: 155 | C55: 230 | D55: BC | E55: 0.135191 | F55: 0.120445 | G55: 54 | H55: 453 | I55: NG_CCS | J55: =VLOOKUP(I55,gen_cost!$A$1:$AY$31,21) -> 0.037998 | K55: =VLOOKUP(I55,gen_cost!$A$1:$AY$31,22) -> 7.16 | L55: =VLOOKUP(I55,gen_cost!$A$1:$AY$31,16) -> 8.54 | M55: =+L55 -> 8.54 | N55: =+M55 -> 8.54 | O55: =+N55 -> 8.54 | P55: =+O55 -> 8.54 | Q55: =+P55 -> 8.54 | R55: =VLOOKUP(I55,gen_cost!$A$1:$AY$31,14) -> 442.87 | S55: =+R55 -> 442.87 | T55: =+S55 -> 442.87 | U55: =+T55 -> 442.87 | V55: =+U55 -> 442.87 | W55: =+V55 -> 442.87 | X55: 20 | Y55: 10
A56: BC_MBO_TSS | B56: 79 | C56: 230 | D56: BC | E56: 0.134644 | F56: 0.11293 | G56: 56 | H56: 438 | I56: NG_CCS | J56: =VLOOKUP(I56,gen_cost!$A$1:$AY$31,21) -> 0.037998 | K56: =VLOOKUP(I56,gen_cost!$A$1:$AY$31,22) -> 7.16 | L56: =VLOOKUP(I56,gen_cost!$A$1:$AY$31,16) -> 8.54 | M56: =+L56 -> 8.54 | N56: =+M56 -> 8.54 | O56: =+N56 -> 8.54 | P56: =+O56 -> 8.54 | Q56: =+P56 -> 8.54 | R56: =VLOOKUP(I56,gen_cost!$A$1:$AY$31,14) -> 442.87 | S56: =+R56 -> 442.87 | T56: =+S56 -> 442.87 | U56: =+T56 -> 442.87 | V56: =+U56 -> 442.87 | W56: =+V56 -> 442.87 | X56: 20 | Y56: 10
A57: BC_MTG_TSS | B57: 97 | C57: 230 | D57: BC | E57: 0.134496 | F57: 0.110456 | G57: 10 | H57: 443 | I57: NG_CCS | J57: =VLOOKUP(I57,gen_cost!$A$1:$AY$31,21) -> 0.037998 | K57: =VLOOKUP(I57,gen_cost!$A$1:$AY$31,22) -> 7.16 | L57: =VLOOKUP(I57,gen_cost!$A$1:$AY$31,16) -> 8.54 | M57: =+L57 -> 8.54 | N57: =+M57 -> 8.54 | O57: =+N57 -> 8.54 | P57: =+O57 -> 8.54 | Q57: =+P57 -> 8.54 | R57: =VLOOKUP(I57,gen_cost!$A$1:$AY$31,14) -> 442.87 | S57: =+R57 -> 442.87 | T57: =+S57 -> 442.87 | U57: =+T57 -> 442.87 | V57: =+U57 -> 442.87 | W57: =+V57 -> 442.87 | X57: 20 | Y57: 10
A58: BC_SVA_DSS | B58: 139 | C58: 230 | D58: BC | E58: 0.143525 | F58: 0.110348 | G58: 11 | H58: 439 | I58: NG_CCS | J58: =VLOOKUP(I58,gen_cost!$A$1:$AY$31,21) -> 0.037998 | K58: =VLOOKUP(I58,gen_cost!$A$1:$AY$31,22) -> 7.16 | L58: =VLOOKUP(I58,gen_cost!$A$1:$AY$31,16) -> 8.54 | M58: =+L58 -> 8.54 | N58: =+M58 -> 8.54 | O58: =+N58 -> 8.54 | P58: =+O58 -> 8.54 | Q58: =+P58 -> 8.54 | R58: =VLOOKUP(I58,gen_cost!$A$1:$AY$31,14) -> 442.87 | S58: =+R58 -> 442.87 | T58: =+S58 -> 442.87 | U58: =+T58 -> 442.87 | V58: =+U58 -> 442.87 | W58: =+V58 -> 442.87 | X58: 20 | Y58: 10
... A61: BC_HWW_JCT | B61: 57 | C61: 230 | D61: BC | E61: 0.130483 | F61: 0.106335 | G61: 56 | H61: 438 | I61: NG_CCS | J61: =VLOOKUP(I61,gen_cost!$A$1:$AY$31,21) -> 0.037998 | K61: =VLOOKUP(I61,gen_cost!$A$1:$AY$31,22) -> 7.16 | L61: =VLOOKUP(I61,gen_cost!$A$1:$AY$31,16) -> 8.54 | M61: =+L61 -> 8.54 | N61: =+M61 -> 8.54 | O61: =+N61 -> 8.54 | P61: =+O61 -> 8.54 | Q61: =+P61 -> 8.54 | R61: =VLOOKUP(I61,gen_cost!$A$1:$AY$31,14) -> 442.87 | S61: =+R61 -> 442.87 | T61: =+S61 -> 442.87 | U61: =+T61 -> 442.87 | V61: =+U61 -> 442.87 | W61: =+V61 -> 442.87 | X61: 20 | Y61: 10
A62: BC_KMI_DSS | B62: 71 | C62: 230 | D62: BC | E62: 0.128186 | F62: 0.10569 | G62: 1 | H62: =B62 -> 71 | I62: wind_onshore | J62: =VLOOKUP(I62,gen_cost!$A$1:$AY$31,21) -> 0 | K62: =VLOOKUP(I62,gen_cost!$A$1:$AY$31,22) -> 0 | L62: =VLOOKUP(I62,gen_cost!$A$1:$AY$31,16) -> 0 | M62: =+L62 -> 0 | N62: =+M62 -> 0 | O62: =+N62 -> 0 | P62: =+O62 -> 0 | Q62: =+P62 -> 0 | R62: =VLOOKUP(I62,gen_cost!$A$1:$AY$31,14) -> 298.39 | S62: =+R62 -> 298.39 | T62: =+S62 -> 298.39 | U62: =+T62 -> 298.39 | V62: =+U62 -> 298.39 | W62: =+V62 -> 298.39 | X62: 20 | Y62: 10
A63: BC_DGB_TSS | B63: 35 | C63: 230 | D63: BC | E63: 0.149561 | F63: 0.104854 | G63: 2 | H63: =B63 -> 35 | I63: wind_onshore | J63: =VLOOKUP(I63,gen_cost!$A$1:$AY$31,21) -> 0 | K63: =VLOOKUP(I63,gen_cost!$A$1:$AY$31,22) -> 0 | L63: =VLOOKUP(I63,gen_cost!$A$1:$AY$31,16) -> 0 | M63: =+L63 -> 0 | N63: =+M63 -> 0 | O63: =+N63 -> 0 | P63: =+O63 -> 0 | Q63: =+P63 -> 0 | R63: =VLOOKUP(I63,gen_cost!$A$1:$AY$31,14) -> 298.39 | S63: =+R63 -> 298.39 | T63: =+S63 -> 298.39 | U63: =+T63 -> 298.39 | V63: =+U63 -> 298.39 | W63: =+V63 -> 298.39 | X63: 20 | Y63: 10
A64: BC_DMR_DSS | B64: 38 | C64: 230 | D64: BC | E64: 0.130586 | F64: 0.10414 | G64: 3 | H64: =B64 -> 38 | I64: wind_onshore | J64: =VLOOKUP(I64,gen_cost!$A$1:$AY$31,21) -> 0 | K64: =VLOOKUP(I64,gen_cost!$A$1:$AY$31,22) -> 0 | L64: =VLOOKUP(I64,gen_cost!$A$1:$AY$31,16) -> 0 | M64: =+L64 -> 0 | N64: =+M64 -> 0 | O64: =+N64 -> 0 | P64: =+O64 -> 0 | Q64: =+P64 -> 0 | R64: =VLOOKUP(I64,gen_cost!$A$1:$AY$31,14) -> 298.39 | S64: =+R64 -> 298.39 | T64: =+S64 -> 298.39 | U64: =+T64 -> 298.39 | V64: =+U64 -> 298.39 | W64: =+V64 -> 298.39 | X64: 20 | Y64: 10
A65: BC_NCT_TSS | B65: 99 | C65: 500 | D65: BC | E65: 0.130802 | F65: 0.103263 | G65: 4 | H65: =B65 -> 99 | I65: wind_onshore | J65: =VLOOKUP(I65,gen_cost!$A$1:$AY$31,21) -> 0 | K65: =VLOOKUP(I65,gen_cost!$A$1:$AY$31,22) -> 0 | L65: =VLOOKUP(I65,gen_cost!$A$1:$AY$31,16) -> 0 | M65: =+L65 -> 0 | N65: =+M65 -> 0 | O65: =+N65 -> 0 | P65: =+O65 -> 0 | Q65: =+P65 -> 0 | R65: =VLOOKUP(I65,gen_cost!$A$1:$AY$31,14) -> 298.39 | S65: =+R65 -> 298.39 | T65: =+S65 -> 298.39 | U65: =+T65 -> 298.39 | V65: =+U65 -> 298.39 | W65: =+V65 -> 298.39 | X65: 20 | Y65: 10
A66: BC_KMO_GSS | B66: 72 | C66: 287 | D66: BC | E66: 0.119154 | F66: 0.102971 | G66: 1 | H66: 461 | I66: solar_PV | J66: =VLOOKUP(I66,gen_cost!$A$1:$AY$31,21) -> 0 | K66: =VLOOKUP(I66,gen_cost!$A$1:$AY$31,22) -> 0 | L66: =VLOOKUP(I66,gen_cost!$A$1:$AY$31,16) -> 0 | M66: =+L66 -> 0 | N66: =+M66 -> 0 | O66: =+N66 -> 0 | P66: =+O66 -> 0 | Q66: =+P66 -> 0 | R66: =VLOOKUP(I66,gen_cost!$A$1:$AY$31,14) -> 201.62 | S66: =+R66 -> 201.62 | T66: =+S66 -> 201.62 | U66: =+T66 -> 201.62 | V66: =+U66 -> 201.62 | W66: =+V66 -> 201.62 | X66: 20 | Y66: 10
A67: BC_HWW_DSS | B67: 56 | C67: 230 | D67: BC | E67: 0.131452 | F67: 0.102728 | G67: 2 | H67: 455 | I67: solar_PV | J67: =VLOOKUP(I67,gen_cost!$A$1:$AY$31,21) -> 0 | K67: =VLOOKUP(I67,gen_cost!$A$1:$AY$31,22) -> 0 | L67: =VLOOKUP(I67,gen_cost!$A$1:$AY$31,16) -> 0 | M67: =+L67 -> 0 | N67: =+M67 -> 0 | O67: =+N67 -> 0 | P67: =+O67 -> 0 | Q67: =+P67 -> 0 | R67: =VLOOKUP(I67,gen_cost!$A$1:$AY$31,14) -> 201.62 | S67: =+R67 -> 201.62 | T67: =+S67 -> 201.62 | U67: =+T67 -> 201.62 | V67: =+U67 -> 201.62 | W67: =+V67 -> 201.62 | X67: 20 | Y67: 10
A68: BC_EUR_ISS | B68: 42 | C68: 287 | D68: BC | E68: 0.111926 | F68: 0.101471 | G68: 3 | H68: 462 | I68: solar_PV | J68: =VLOOKUP(I68,gen_cost!$A$1:$AY$31,21) -> 0 | K68: =VLOOKUP(I68,gen_cost!$A$1:$AY$31,22) -> 0 | L68: =VLOOKUP(I68,gen_cost!$A$1:$AY$31,16) -> 0 | M68: =+L68 -> 0 | N68: =+M68 -> 0 | O68: =+N68 -> 0 | P68: =+O68 -> 0 | Q68: =+P68 -> 0 | R68: =VLOOKUP(I68,gen_cost!$A$1:$AY$31,14) -> 201.62 | S68: =+R68 -> 201.62 | T68: =+S68 -> 201.62 | U68: =+T68 -> 201.62 | V68: =+U68 -> 201.62 | W68: =+V68 -> 201.62 | X68: 20 | Y68: 10
A69: BC_KIT_DSS | B69: 69 | C69: 287 | D69: BC | E69: 0.111926 | F69: 0.101471 | G69: 4 | H69: 454 | I69: solar_PV | J69: =VLOOKUP(I69,gen_cost!$A$1:$AY$31,21) -> 0 | K69: =VLOOKUP(I69,gen_cost!$A$1:$AY$31,22) -> 0 | L69: =VLOOKUP(I69,gen_cost!$A$1:$AY$31,16) -> 0 | M69: =+L69 -> 0 | N69: =+M69 -> 0 | O69: =+N69 -> 0 | P69: =+O69 -> 0 | Q69: =+P69 -> 0 | R69: =VLOOKUP(I69,gen_cost!$A$1:$AY$31,14) -> 201.62 | S69: =+R69 -> 201.62 | T69: =+S69 -> 201.62 | U69: =+T69 -> 201.62 | V69: =+U69 -> 201.62 | W69: =+V69 -> 201.62 | X69: 20 | Y69: 10
A70: BC_KTB_ISS | B70: 73 | C70: 287 | D70: BC | E70: 0.111926 | F70: 0.101471 | G70: 1 | H70: 461 | I70: solar_PV | J70: =VLOOKUP(I70,gen_cost!$A$1:$AY$31,21) -> 0 | K70: =VLOOKUP(I70,gen_cost!$A$1:$AY$31,22) -> 0 | L70: =VLOOKUP(I70,gen_cost!$A$1:$AY$31,16) -> 0 | M70: =+L70 -> 0 | N70: =+M70 -> 0 | O70: =+N70 -> 0 | P70: =+O70 -> 0 | Q70: =+P70 -> 0 | R70: =VLOOKUP(I70,gen_cost!$A$1:$AY$31,14) -> 201.62 | S70: =+R70 -> 201.62 | T70: =+S70 -> 201.62 | U70: =+T70 -> 201.62 | V70: =+U70 -> 201.62 | W70: =+V70 -> 201.62 | X70: 20 | Y70: 10
A71: BC_MIN_DSS | B71: 82 | C71: 230 | D71: BC | E71: 0.111963 | F71: 0.099865 | G71: 2 | H71: 455 | I71: NG_CCS | J71: =VLOOKUP(I71,gen_cost!$A$1:$AY$31,21) -> 0.037998 | K71: =VLOOKUP(I71,gen_cost!$A$1:$AY$31,22) -> 7.16 | L71: =VLOOKUP(I71,gen_cost!$A$1:$AY$31,16) -> 8.54 | M71: =+L71 -> 8.54 | N71: =+M71 -> 8.54 | O71: =+N71 -> 8.54 | P71: =+O71 -> 8.54 | Q71: =+P71 -> 8.54 | R71: =VLOOKUP(I71,gen_cost!$A$1:$AY$31,14) -> 442.87 | S71: =+R71 -> 442.87 | T71: =+S71 -> 442.87 | U71: =+T71 -> 442.87 | V71: =+U71 -> 442.87 | W71: =+V71 -> 442.87 | X71: 20 | Y71: 10
A72: BC_VVW_DSS | B72: 159 | C72: 230 | D72: BC | E72: 0.141002 | F72: 0.098312 | G72: 3 | H72: 462 | I72: NG_CCS | J72: =VLOOKUP(I72,gen_cost!$A$1:$AY$31,21) -> 0.037998 | K72: =VLOOKUP(I72,gen_cost!$A$1:$AY$31,22) -> 7.16 | L72: =VLOOKUP(I72,gen_cost!$A$1:$AY$31,16) -> 8.54 | M72: =+L72 -> 8.54 | N72: =+M72 -> 8.54 | O72: =+N72 -> 8.54 | P72: =+O72 -> 8.54 | Q72: =+P72 -> 8.54 | R72: =VLOOKUP(I72,gen_cost!$A$1:$AY$31,14) -> 442.87 | S72: =+R72 -> 442.87 | T72: =+S72 -> 442.87 | U72: =+T72 -> 442.87 | V72: =+U72 -> 442.87 | W72: =+V72 -> 442.87 | X72: 20 | Y72: 10
A73: BC_EBT_TSS | B73: 39 | C73: 230 | D73: BC | E73: 0.133367 | F73: 0.098279 | G73: 4 | H73: 454 | I73: NG_CCS | J73: =VLOOKUP(I73,gen_cost!$A$1:$AY$31,21) -> 0.037998 | K73: =VLOOKUP(I73,gen_cost!$A$1:$AY$31,22) -> 7.16 | L73: =VLOOKUP(I73,gen_cost!$A$1:$AY$31,16) -> 8.54 | M73: =+L73 -> 8.54 | N73: =+M73 -> 8.54 | O73: =+N73 -> 8.54 | P73: =+O73 -> 8.54 | Q73: =+P73 -> 8.54 | R73: =VLOOKUP(I73,gen_cost!$A$1:$AY$31,14) -> 442.87 | S73: =+R73 -> 442.87 | T73: =+S73 -> 442.87 | U73: =+T73 -> 442.87 | V73: =+U73 -> 442.87 | W73: =+V73 -> 442.87 | X73: 20 | Y73: 10
A74: BC_TXW_TSS | B74: 151 | C74: 500 | D74: BC | E74: 0.13118 | F74: 0.096201 | G74: 1 | H74: 461 | I74: NG_CCS | J74: =VLOOKUP(I74,gen_cost!$A$1:$AY$31,21) -> 0.037998 | K74: =VLOOKUP(I74,gen_cost!$A$1:$AY$31,22) -> 7.16 | L74: =VLOOKUP(I74,gen_cost!$A$1:$AY$31,16) -> 8.54 | M74: =+L74 -> 8.54 | N74: =+M74 -> 8.54 | O74: =+N74 -> 8.54 | P74: =+O74 -> 8.54 | Q74: =+P74 -> 8.54 | R74: =VLOOKUP(I74,gen_cost!$A$1:$AY$31,14) -> 442.87 | S74: =+R74 -> 442.87 | T74: =+S74 -> 442.87 | U74: =+T74 -> 442.87 | V74: =+U74 -> 442.87 | W74: =+V74 -> 442.87 | X74: 20 | Y74: 10
A75: BC_MLE_DSS | B75: 85 | C75: 230 | D75: BC | E75: 0.13099 | F75: 0.094923 | G75: 2 | H75: 455 | I75: NG_CCS | J75: =VLOOKUP(I75,gen_cost!$A$1:$AY$31,21) -> 0.037998 | K75: =VLOOKUP(I75,gen_cost!$A$1:$AY$31,22) -> 7.16 | L75: =VLOOKUP(I75,gen_cost!$A$1:$AY$31,16) -> 8.54 | M75: =+L75 -> 8.54 | N75: =+M75 -> 8.54 | O75: =+N75 -> 8.54 | P75: =+O75 -> 8.54 | Q75: =+P75 -> 8.54 | R75: =VLOOKUP(I75,gen_cost!$A$1:$AY$31,14) -> 442.87 | S75: =+R75 -> 442.87 | T75: =+S75 -> 442.87 | U75: =+T75 -> 442.87 | V75: =+U75 -> 442.87 | W75: =+V75 -> 442.87 | X75: 20 | Y75: 10
A76: BC_MLN_DSS | B76: 86 | C76: 230 | D76: BC | E76: 0.130364 | F76: 0.092492 | G76: 3 | H76: 462 | I76: NG_CCS | J76: =VLOOKUP(I76,gen_cost!$A$1:$AY$31,21) -> 0.037998 | K76: =VLOOKUP(I76,gen_cost!$A$1:$AY$31,22) -> 7.16 | L76: =VLOOKUP(I76,gen_cost!$A$1:$AY$31,16) -> 8.54 | M76: =+L76 -> 8.54 | N76: =+M76 -> 8.54 | O76: =+N76 -> 8.54 | P76: =+O76 -> 8.54 | Q76: =+P76 -> 8.54 | R76: =VLOOKUP(I76,gen_cost!$A$1:$AY$31,14) -> 442.87 | S76: =+R76 -> 442.87 | T76: =+S76 -> 442.87 | U76: =+T76 -> 442.87 | V76: =+U76 -> 442.87 | W76: =+V76 -> 442.87 | X76: 20 | Y76: 10
A77: BC_CBN_DSS | B77: 27 | C77: 230 | D77: BC | E77: 0.131233 | F77: 0.08918 | G77: 4 | H77: 454 | I77: NG_CCS | J77: =VLOOKUP(I77,gen_cost!$A$1:$AY$31,21) -> 0.037998 | K77: =VLOOKUP(I77,gen_cost!$A$1:$AY$31,22) -> 7.16 | L77: =VLOOKUP(I77,gen_cost!$A$1:$AY$31,16) -> 8.54 | M77: =+L77 -> 8.54 | N77: =+M77 -> 8.54 | O77: =+N77 -> 8.54 | P77: =+O77 -> 8.54 | Q77: =+P77 -> 8.54 | R77: =VLOOKUP(I77,gen_cost!$A$1:$AY$31,14) -> 442.87 | S77: =+R77 -> 442.87 | T77: =+S77 -> 442.87 | U77: =+T77 -> 442.87 | V77: =+U77 -> 442.87 | W77: =+V77 -> 442.87 | X77: 20 | Y77: 10
A78: BC_ARN_DSS | B78: 5 | C78: 230 | D78: BC | E78: 0.131679 | F78: 0.088419 | G78: 22 | H78: =B78 -> 5 | I78: wind_onshore | J78: =VLOOKUP(I78,gen_cost!$A$1:$AY$31,21) -> 0 | K78: =VLOOKUP(I78,gen_cost!$A$1:$AY$31,22) -> 0 | L78: =VLOOKUP(I78,gen_cost!$A$1:$AY$31,16) -> 0 | M78: =+L78 -> 0 | N78: =+M78 -> 0 | O78: =+N78 -> 0 | P78: =+O78 -> 0 | Q78: =+P78 -> 0 | R78: =VLOOKUP(I78,gen_cost!$A$1:$AY$31,14) -> 298.39 | S78: =+R78 -> 298.39 | T78: =+S78 -> 298.39 | U78: =+T78 -> 298.39 | V78: =+U78 -> 298.39 | W78: =+V78 -> 298.39 | X78: 20 | Y78: 10
A79: BC_TIR_TSS | B79: 146 | C79: 500 | D79: BC | E79: 0.130641 | F79: 0.08786 | G79: 23 | H79: =B79 -> 146 | I79: wind_onshore | J79: =VLOOKUP(I79,gen_cost!$A$1:$AY$31,21) -> 0 | K79: =VLOOKUP(I79,gen_cost!$A$1:$AY$31,22) -> 0 | L79: =VLOOKUP(I79,gen_cost!$A$1:$AY$31,16) -> 0 | M79: =+L79 -> 0 | N79: =+M79 -> 0 | O79: =+N79 -> 0 | P79: =+O79 -> 0 | Q79: =+P79 -> 0 | R79: =VLOOKUP(I79,gen_cost!$A$1:$AY$31,14) -> 298.39 | S79: =+R79 -> 298.39 | T79: =+S79 -> 298.39 | U79: =+T79 -> 298.39 | V79: =+U79 -> 298.39 | W79: =+V79 -> 298.39 | X79: 20 | Y79: 10
A80: BC_TXE_TSS | B80: 150 | C80: 500 | D80: BC | E80: 0.130641 | F80: 0.08786 | G80: 24 | H80: =B80 -> 150 | I80: wind_onshore | J80: =VLOOKUP(I80,gen_cost!$A$1:$AY$31,21) -> 0 | K80: =VLOOKUP(I80,gen_cost!$A$1:$AY$31,22) -> 0 | L80: =VLOOKUP(I80,gen_cost!$A$1:$AY$31,16) -> 0 | M80: =+L80 -> 0 | N80: =+M80 -> 0 | O80: =+N80 -> 0 | P80: =+O80 -> 0 | Q80: =+P80 -> 0 | R80: =VLOOKUP(I80,gen_cost!$A$1:$AY$31,14) -> 298.39 | S80: =+R80 -> 298.39 | T80: =+S80 -> 298.39 | U80: =+T80 -> 298.39 | V80: =+U80 -> 298.39 | W80: =+V80 -> 298.39 | X80: 20 | Y80: 10
A81: BC_KLY_DSS | B81: 70 | C81: 230 | D81: BC | E81: 0.146647 | F81: 0.087026 | G81: 25 | H81: =B81 -> 70 | I81: wind_onshore | J81: =VLOOKUP(I81,gen_cost!$A$1:$AY$31,21) -> 0 | K81: =VLOOKUP(I81,gen_cost!$A$1:$AY$31,22) -> 0 | L81: =VLOOKUP(I81,gen_cost!$A$1:$AY$31,16) -> 0 | M81: =+L81 -> 0 | N81: =+M81 -> 0 | O81: =+N81 -> 0 | P81: =+O81 -> 0 | Q81: =+P81 -> 0 | R81: =VLOOKUP(I81,gen_cost!$A$1:$AY$31,14) -> 298.39 | S81: =+R81 -> 298.39 | T81: =+S81 -> 298.39 | U81: =+T81 -> 298.39 | V81: =+U81 -> 298.39 | W81: =+V81 -> 298.39 | X81: 20 | Y81: 10
A82: BC_RGA_TSS | B82: 117 | C82: 230 | D82: BC | E82: 0.146841 | F82: 0.086304 | G82: 26 | H82: =B82 -> 117 | I82: wind_onshore | J82: =VLOOKUP(I82,gen_cost!$A$1:$AY$31,21) -> 0 | K82: =VLOOKUP(I82,gen_cost!$A$1:$AY$31,22) -> 0 | L82: =VLOOKUP(I82,gen_cost!$A$1:$AY$31,16) -> 0 | M82: =+L82 -> 0 | N82: =+M82 -> 0 | O82: =+N82 -> 0 | P82: =+O82 -> 0 | Q82: =+P82 -> 0 | R82: =VLOOKUP(I82,gen_cost!$A$1:$AY$31,14) -> 298.39 | S82: =+R82 -> 298.39 | T82: =+S82 -> 298.39 | U82: =+T82 -> 298.39 | V82: =+U82 -> 298.39 | W82: =+V82 -> 298.39 | X82: 20 | Y82: 10
A83: BC_FLW_DSS | B83: 45 | C83: 230 | D83: BC | E83: 0.129906 | F83: 0.08563 | G83: 27 | H83: =B83 -> 45 | I83: wind_onshore | J83: =VLOOKUP(I83,gen_cost!$A$1:$AY$31,21) -> 0 | K83: =VLOOKUP(I83,gen_cost!$A$1:$AY$31,22) -> 0 | L83: =VLOOKUP(I83,gen_cost!$A$1:$AY$31,16) -> 0 | M83: =+L83 -> 0 | N83: =+M83 -> 0 | O83: =+N83 -> 0 | P83: =+O83 -> 0 | Q83: =+P83 -> 0 | R83: =VLOOKUP(I83,gen_cost!$A$1:$AY$31,14) -> 298.39 | S83: =+R83 -> 298.39 | T83: =+S83 -> 298.39 | U83: =+T83 -> 298.39 | V83: =+U83 -> 298.39 | W83: =+V83 -> 298.39 | X83: 20 | Y83: 10
A84: BC_SYH_DSS | B84: 141 | C84: 230 | D84: BC | E84: 0.130224 | F84: 0.084632 | G84: 28 | H84: =B84 -> 141 | I84: wind_onshore | J84: =VLOOKUP(I84,gen_cost!$A$1:$AY$31,21) -> 0 | K84: =VLOOKUP(I84,gen_cost!$A$1:$AY$31,22) -> 0 | L84: =VLOOKUP(I84,gen_cost!$A$1:$AY$31,16) -> 0 | M84: =+L84 -> 0 | N84: =+M84 -> 0 | O84: =+N84 -> 0 | P84: =+O84 -> 0 | Q84: =+P84 -> 0 | R84: =VLOOKUP(I84,gen_cost!$A$1:$AY$31,14) -> 298.39 | S84: =+R84 -> 298.39 | T84: =+S84 -> 298.39 | U84: =+T84 -> 298.39 | V84: =+U84 -> 298.39 | W84: =+V84 -> 298.39 | X84: 20 | Y84: 10
A85: BC_SYH_JCT | B85: 142 | C85: 230 | D85: BC | E85: 0.130212 | F85: 0.084563 | G85: 29 | H85: =B85 -> 142 | I85: wind_onshore | J85: =VLOOKUP(I85,gen_cost!$A$1:$AY$31,21) -> 0 | K85: =VLOOKUP(I85,gen_cost!$A$1:$AY$31,22) -> 0 | L85: =VLOOKUP(I85,gen_cost!$A$1:$AY$31,16) -> 0 | M85: =+L85 -> 0 | N85: =+M85 -> 0 | O85: =+N85 -> 0 | P85: =+O85 -> 0 | Q85: =+P85 -> 0 | R85: =VLOOKUP(I85,gen_cost!$A$1:$AY$31,14) -> 298.39 | S85: =+R85 -> 298.39 | T85: =+S85 -> 298.39 | U85: =+T85 -> 298.39 | V85: =+U85 -> 298.39 | W85: =+V85 -> 298.39 | X85: 20 | Y85: 10
A86: BC_STV_DSS | B86: 138 | C86: 230 | D86: BC | E86: 0.131457 | F86: 0.083808 | G86: 30 | H86: =B86 -> 138 | I86: wind_onshore | J86: =VLOOKUP(I86,gen_cost!$A$1:$AY$31,21) -> 0 | K86: =VLOOKUP(I86,gen_cost!$A$1:$AY$31,22) -> 0 | L86: =VLOOKUP(I86,gen_cost!$A$1:$AY$31,16) -> 0 | M86: =+L86 -> 0 | N86: =+M86 -> 0 | O86: =+N86 -> 0 | P86: =+O86 -> 0 | Q86: =+P86 -> 0 | R86: =VLOOKUP(I86,gen_cost!$A$1:$AY$31,14) -> 298.39 | S86: =+R86 -> 298.39 | T86: =+S86 -> 298.39 | U86: =+T86 -> 298.39 | V86: =+U86 -> 298.39 | W86: =+V86 -> 298.39 | X86: 20 | Y86: 10
A87: BC_ING_DSS | B87: 59 | C87: 230 | D87: BC | E87: 0.129828 | F87: 0.082032 | G87: 31 | H87: =B87 -> 59 | I87: wind_onshore | J87: =VLOOKUP(I87,gen_cost!$A$1:$AY$31,21) -> 0 | K87: =VLOOKUP(I87,gen_cost!$A$1:$AY$31,22) -> 0 | L87: =VLOOKUP(I87,gen_cost!$A$1:$AY$31,16) -> 0 | M87: =+L87 -> 0 | N87: =+M87 -> 0 | O87: =+N87 -> 0 | P87: =+O87 -> 0 | Q87: =+P87 -> 0 | R87: =VLOOKUP(I87,gen_cost!$A$1:$AY$31,14) -> 298.39 | S87: =+R87 -> 298.39 | T87: =+S87 -> 298.39 | U87: =+T87 -> 298.39 | V87: =+U87 -> 298.39 | W87: =+V87 -> 298.39 | X87: 20 | Y87: 10
A88: BC_CBK_DSS | B88: 26 | C88: 230 | D88: BC | E88: 0.166083 | F88: 0.081028 | G88: 34 | H88: =B88 -> 26 | I88: wind_onshore | J88: =VLOOKUP(I88,gen_cost!$A$1:$AY$31,21) -> 0 | K88: =VLOOKUP(I88,gen_cost!$A$1:$AY$31,22) -> 0 | L88: =VLOOKUP(I88,gen_cost!$A$1:$AY$31,16) -> 0 | M88: =+L88 -> 0 | N88: =+M88 -> 0 | O88: =+N88 -> 0 | P88: =+O88 -> 0 | Q88: =+P88 -> 0 | R88: =VLOOKUP(I88,gen_cost!$A$1:$AY$31,14) -> 298.39 | S88: =+R88 -> 298.39 | T88: =+S88 -> 298.39 | U88: =+T88 -> 298.39 | V88: =+U88 -> 298.39 | W88: =+V88 -> 298.39 | X88: 20 | Y88: 10
A89: BC_CCB_TSS | B89: 28 | C89: 500 | D89: BC | E89: 0.130276 | F89: 0.079095 | G89: 35 | H89: =B89 -> 28 | I89: wind_onshore | J89: =VLOOKUP(I89,gen_cost!$A$1:$AY$31,21) -> 0 | K89: =VLOOKUP(I89,gen_cost!$A$1:$AY$31,22) -> 0 | L89: =VLOOKUP(I89,gen_cost!$A$1:$AY$31,16) -> 0 | M89: =+L89 -> 0 | N89: =+M89 -> 0 | O89: =+N89 -> 0 | P89: =+O89 -> 0 | Q89: =+P89 -> 0 | R89: =VLOOKUP(I89,gen_cost!$A$1:$AY$31,14) -> 298.39 | S89: =+R89 -> 298.39 | T89: =+S89 -> 298.39 | U89: =+T89 -> 298.39 | V89: =+U89 -> 298.39 | W89: =+V89 -> 298.39 | X89: 20 | Y89: 10
... A126: BC_WAX_GSS | B126: 161 | C126: 230 | D126: BC | E126: 0.150723 | F126: 0.052855 | G126: 99 | H126: =B126 -> 161 | I126: wind_onshore | J126: =VLOOKUP(I126,gen_cost!$A$1:$AY$31,21) -> 0 | K126: =VLOOKUP(I126,gen_cost!$A$1:$AY$31,22) -> 0 | L126: =VLOOKUP(I126,gen_cost!$A$1:$AY$31,16) -> 0 | M126: =+L126 -> 0 | N126: =+M126 -> 0 | O126: =+N126 -> 0 | P126: =+O126 -> 0 | Q126: =+P126 -> 0 | R126: =VLOOKUP(I126,gen_cost!$A$1:$AY$31,14) -> 298.39 | S126: =+R126 -> 298.39 | T126: =+S126 -> 298.39 | U126: =+T126 -> 298.39 | V126: =+U126 -> 298.39 | W126: =+V126 -> 298.39 | X126: 20 | Y126: 10
A127: BC_WHS_TSS | B127: 162 | C127: 230 | D127: BC | E127: 0.150723 | F127: 0.052855 | G127: 22 | H127: 573 | I127: solar_PV | J127: =VLOOKUP(I127,gen_cost!$A$1:$AY$31,21) -> 0 | K127: =VLOOKUP(I127,gen_cost!$A$1:$AY$31,22) -> 0 | L127: =VLOOKUP(I127,gen_cost!$A$1:$AY$31,16) -> 0 | M127: =+L127 -> 0 | N127: =+M127 -> 0 | O127: =+N127 -> 0 | P127: =+O127 -> 0 | Q127: =+P127 -> 0 | R127: =VLOOKUP(I127,gen_cost!$A$1:$AY$31,14) -> 201.62 | S127: =+R127 -> 201.62 | T127: =+S127 -> 201.62 | U127: =+T127 -> 201.62 | V127: =+U127 -> 201.62 | W127: =+V127 -> 201.62 | X127: 20 | Y127: 10
A128: BC_BR1_GSS | B128: 18 | C128: 230 | D128: BC | E128: 0.14859 | F128: 0.051989 | G128: 23 | H128: 501 | I128: solar_PV | J128: =VLOOKUP(I128,gen_cost!$A$1:$AY$31,21) -> 0 | K128: =VLOOKUP(I128,gen_cost!$A$1:$AY$31,22) -> 0 | L128: =VLOOKUP(I128,gen_cost!$A$1:$AY$31,16) -> 0 | M128: =+L128 -> 0 | N128: =+M128 -> 0 | O128: =+N128 -> 0 | P128: =+O128 -> 0 | Q128: =+P128 -> 0 | R128: =VLOOKUP(I128,gen_cost!$A$1:$AY$31,14) -> 201.62 | S128: =+R128 -> 201.62 | T128: =+S128 -> 201.62 | U128: =+T128 -> 201.62 | V128: =+U128 -> 201.62 | W128: =+V128 -> 201.62 | X128: 20 | Y128: 10
A129: BC_BR2_GSS | B129: 19 | C129: 360 | D129: BC | E129: 0.14859 | F129: 0.051989 | G129: 24 | H129: 505 | I129: solar_PV | J129: =VLOOKUP(I129,gen_cost!$A$1:$AY$31,21) -> 0 | K129: =VLOOKUP(I129,gen_cost!$A$1:$AY$31,22) -> 0 | L129: =VLOOKUP(I129,gen_cost!$A$1:$AY$31,16) -> 0 | M129: =+L129 -> 0 | N129: =+M129 -> 0 | O129: =+N129 -> 0 | P129: =+O129 -> 0 | Q129: =+P129 -> 0 | R129: =VLOOKUP(I129,gen_cost!$A$1:$AY$31,14) -> 201.62 | S129: =+R129 -> 201.62 | T129: =+S129 -> 201.62 | U129: =+T129 -> 201.62 | V129: =+U129 -> 201.62 | W129: =+V129 -> 201.62 | X129: 20 | Y129: 10
A130: BC_SEV_GSS | B130: 129 | C130: 230 | D130: BC | E130: 0.150268 | F130: 0.051907 | G130: 25 | H130: 500 | I130: solar_PV | J130: =VLOOKUP(I130,gen_cost!$A$1:$AY$31,21) -> 0 | K130: =VLOOKUP(I130,gen_cost!$A$1:$AY$31,22) -> 0 | L130: =VLOOKUP(I130,gen_cost!$A$1:$AY$31,16) -> 0 | M130: =+L130 -> 0 | N130: =+M130 -> 0 | O130: =+N130 -> 0 | P130: =+O130 -> 0 | Q130: =+P130 -> 0 | R130: =VLOOKUP(I130,gen_cost!$A$1:$AY$31,14) -> 201.62 | S130: =+R130 -> 201.62 | T130: =+S130 -> 201.62 | U130: =+T130 -> 201.62 | V130: =+U130 -> 201.62 | W130: =+V130 -> 201.62 | X130: 20 | Y130: 10
A131: BC_BRT_TSS | B131: 20 | C131: 230 | D131: BC | E131: 0.148653 | F131: 0.051453 | G131: 26 | H131: 502 | I131: solar_PV | J131: =VLOOKUP(I131,gen_cost!$A$1:$AY$31,21) -> 0 | K131: =VLOOKUP(I131,gen_cost!$A$1:$AY$31,22) -> 0 | L131: =VLOOKUP(I131,gen_cost!$A$1:$AY$31,16) -> 0 | M131: =+L131 -> 0 | N131: =+M131 -> 0 | O131: =+N131 -> 0 | P131: =+O131 -> 0 | Q131: =+P131 -> 0 | R131: =VLOOKUP(I131,gen_cost!$A$1:$AY$31,14) -> 201.62 | S131: =+R131 -> 201.62 | T131: =+S131 -> 201.62 | U131: =+T131 -> 201.62 | V131: =+U131 -> 201.62 | W131: =+V131 -> 201.62 | X131: 20 | Y131: 10
A132: BC_SEL_TSS | B132: 128 | C132: 230 | D132: BC | E132: 0.150138 | F132: 0.049536 | G132: 27 | H132: 803 | I132: solar_PV | J132: =VLOOKUP(I132,gen_cost!$A$1:$AY$31,21) -> 0 | K132: =VLOOKUP(I132,gen_cost!$A$1:$AY$31,22) -> 0 | L132: =VLOOKUP(I132,gen_cost!$A$1:$AY$31,16) -> 0 | M132: =+L132 -> 0 | N132: =+M132 -> 0 | O132: =+N132 -> 0 | P132: =+O132 -> 0 | Q132: =+P132 -> 0 | R132: =VLOOKUP(I132,gen_cost!$A$1:$AY$31,14) -> 201.62 | S132: =+R132 -> 201.62 | T132: =+S132 -> 201.62 | U132: =+T132 -> 201.62 | V132: =+U132 -> 201.62 | W132: =+V132 -> 201.62 | X132: 20 | Y132: 10
A133: BC_VOL_GSS | B133: 157 | C133: 287 | D133: BC | E133: 0.112674 | F133: 0.04934 | G133: 28 | H133: 901 | I133: solar_PV | J133: =VLOOKUP(I133,gen_cost!$A$1:$AY$31,21) -> 0 | K133: =VLOOKUP(I133,gen_cost!$A$1:$AY$31,22) -> 0 | L133: =VLOOKUP(I133,gen_cost!$A$1:$AY$31,16) -> 0 | M133: =+L133 -> 0 | N133: =+M133 -> 0 | O133: =+N133 -> 0 | P133: =+O133 -> 0 | Q133: =+P133 -> 0 | R133: =VLOOKUP(I133,gen_cost!$A$1:$AY$31,14) -> 201.62 | S133: =+R133 -> 201.62 | T133: =+S133 -> 201.62 | U133: =+T133 -> 201.62 | V133: =+U133 -> 201.62 | W133: =+V133 -> 201.62 | X133: 20 | Y133: 10
A134: BC_VOL_JCT | B134: 158 | C134: 287 | D134: BC | E134: 0.112674 | F134: 0.04934 | G134: 29 | H134: 900 | I134: solar_PV | J134: =VLOOKUP(I134,gen_cost!$A$1:$AY$31,21) -> 0 | K134: =VLOOKUP(I134,gen_cost!$A$1:$AY$31,22) -> 0 | L134: =VLOOKUP(I134,gen_cost!$A$1:$AY$31,16) -> 0 | M134: =+L134 -> 0 | N134: =+M134 -> 0 | O134: =+N134 -> 0 | P134: =+O134 -> 0 | Q134: =+P134 -> 0 | R134: =VLOOKUP(I134,gen_cost!$A$1:$AY$31,14) -> 201.62 | S134: =+R134 -> 201.62 | T134: =+S134 -> 201.62 | U134: =+T134 -> 201.62 | V134: =+U134 -> 201.62 | W134: =+V134 -> 201.62 | X134: 20 | Y134: 10
A135: BC_FKR_GSS | B135: 44 | C135: 287 | D135: BC | E135: 0.11148 | F135: 0.049045 | G135: 30 | H135: 730 | I135: solar_PV | J135: =VLOOKUP(I135,gen_cost!$A$1:$AY$31,21) -> 0 | K135: =VLOOKUP(I135,gen_cost!$A$1:$AY$31,22) -> 0 | L135: =VLOOKUP(I135,gen_cost!$A$1:$AY$31,16) -> 0 | M135: =+L135 -> 0 | N135: =+M135 -> 0 | O135: =+N135 -> 0 | P135: =+O135 -> 0 | Q135: =+P135 -> 0 | R135: =VLOOKUP(I135,gen_cost!$A$1:$AY$31,14) -> 201.62 | S135: =+R135 -> 201.62 | T135: =+S135 -> 201.62 | U135: =+T135 -> 201.62 | V135: =+U135 -> 201.62 | W135: =+V135 -> 201.62 | X135: 20 | Y135: 10
A136: BC_WTS_TSS | B136: 166 | C136: 230 | D136: BC | E136: 0.15074 | F136: 0.046364 | G136: 31 | H136: 731 | I136: solar_PV | J136: =VLOOKUP(I136,gen_cost!$A$1:$AY$31,21) -> 0 | K136: =VLOOKUP(I136,gen_cost!$A$1:$AY$31,22) -> 0 | L136: =VLOOKUP(I136,gen_cost!$A$1:$AY$31,16) -> 0 | M136: =+L136 -> 0 | N136: =+M136 -> 0 | O136: =+N136 -> 0 | P136: =+O136 -> 0 | Q136: =+P136 -> 0 | R136: =VLOOKUP(I136,gen_cost!$A$1:$AY$31,14) -> 201.62 | S136: =+R136 -> 201.62 | T136: =+S136 -> 201.62 | U136: =+T136 -> 201.62 | V136: =+U136 -> 201.62 | W136: =+V136 -> 201.62 | X136: 20 | Y136: 10
A137: BC_ACK_DSS | B137: 2 | C137: 230 | D137: BC | E137: 0.145822 | F137: 0.040198 | G137: 34 | H137: 488 | I137: solar_PV | J137: =VLOOKUP(I137,gen_cost!$A$1:$AY$31,21) -> 0 | K137: =VLOOKUP(I137,gen_cost!$A$1:$AY$31,22) -> 0 | L137: =VLOOKUP(I137,gen_cost!$A$1:$AY$31,16) -> 0 | M137: =+L137 -> 0 | N137: =+M137 -> 0 | O137: =+N137 -> 0 | P137: =+O137 -> 0 | Q137: =+P137 -> 0 | R137: =VLOOKUP(I137,gen_cost!$A$1:$AY$31,14) -> 201.62 | S137: =+R137 -> 201.62 | T137: =+S137 -> 201.62 | U137: =+T137 -> 201.62 | V137: =+U137 -> 201.62 | W137: =+V137 -> 201.62 | X137: 20 | Y137: 10
A138: BC_ULR_GSS | B138: 153 | C138: 230 | D138: BC | E138: 0.150975 | F138: 0.040025 | G138: 35 | H138: 487 | I138: solar_PV | J138: =VLOOKUP(I138,gen_cost!$A$1:$AY$31,21) -> 0 | K138: =VLOOKUP(I138,gen_cost!$A$1:$AY$31,22) -> 0 | L138: =VLOOKUP(I138,gen_cost!$A$1:$AY$31,16) -> 0 | M138: =+L138 -> 0 | N138: =+M138 -> 0 | O138: =+N138 -> 0 | P138: =+O138 -> 0 | Q138: =+P138 -> 0 | R138: =VLOOKUP(I138,gen_cost!$A$1:$AY$31,14) -> 201.62 | S138: =+R138 -> 201.62 | T138: =+S138 -> 201.62 | U138: =+T138 -> 201.62 | V138: =+U138 -> 201.62 | W138: =+V138 -> 201.62 | X138: 20 | Y138: 10
... A167: BC_ILL_DSS | B167: 58 | C167: 230 | D167: BC | E167: 0.154267 | F167: 0.020917 | G167: 90 | H167: 556 | I167: solar_PV | J167: =VLOOKUP(I167,gen_cost!$A$1:$AY$31,21) -> 0 | K167: =VLOOKUP(I167,gen_cost!$A$1:$AY$31,22) -> 0 | L167: =VLOOKUP(I167,gen_cost!$A$1:$AY$31,16) -> 0 | M167: =+L167 -> 0 | N167: =+M167 -> 0 | O167: =+N167 -> 0 | P167: =+O167 -> 0 | Q167: =+P167 -> 0 | R167: =VLOOKUP(I167,gen_cost!$A$1:$AY$31,14) -> 201.62 | S167: =+R167 -> 201.62 | T167: =+S167 -> 201.62 | U167: =+T167 -> 201.62 | V167: =+U167 -> 201.62 | W167: =+V167 -> 201.62 | X167: 20 | Y167: 10

Sheet lines
A1: ID | B1: province | C1: number_of_circuits | D1: network_node_code_starting | E1: network_node_code_ending | F1: voltage | G1: line_length_km | H1: reactance | I1: ttc_summer | J1: ttc_winter | K1: From | L1: To | M1: x_pu | N1: Susceptance | O1: Capacity
A2: 1 | B2: BC | C2: 1 | D2: BC_AAL_DSS | E2: BC_CBK_DSS | F2: 230 | G2: 161.71 | H2: 77.62 | I2: 397 | J2: 457 | K2: =VLOOKUP(D2,nodes!$A$1:$K$167,2) -> 1 | L2: =VLOOKUP(E2,nodes!$A$1:$K$167,2) -> 26 | M2: =H2/(F2^2/100) -> 0.14672968 | N2: =1/M2 -> 6.8152538 | O2: =J2/100 -> 4.57
A3: 2 | B3: BC | C3: 1 | D3: BC_ACK_DSS | E3: BC_SAM_DSS | F3: 230 | G3: 37.586 | H3: 18.04 | I3: 385 | J3: 461 | K3: =VLOOKUP(D3,nodes!$A$1:$K$167,2) -> 2 | L3: =VLOOKUP(E3,nodes!$A$1:$K$167,2) -> 123 | M3: =H3/(F3^2/100) -> 0.034102079 | N3: =1/M3 -> 29.323725 | O3: =J3/100 -> 4.61
A4: 3 | B4: BC | C4: 1 | D4: BC_ACK_DSS | E4: BC_VNT_TSS | F4: 230 | G4: 49.909 | H4: 23.96 | I4: 383 | J4: 461 | K4: =VLOOKUP(D4,nodes!$A$1:$K$167,2) -> 2 | L4: =VLOOKUP(E4,nodes!$A$1:$K$167,2) -> 156 | M4: =H4/(F4^2/100) -> 0.045293006 | N4: =1/M4 -> 22.078464 | O4: =J4/100 -> 4.61
A5: 4 | B5: BC | C5: 1 | D5: BC_ACK_DSS | E5: BC_VNT_TSS | F5: 230 | G5: 49.957 | H5: 23.98 | I5: 383 | J5: 460 | K5: =VLOOKUP(D5,nodes!$A$1:$K$167,2) -> 2 | L5: =VLOOKUP(E5,nodes!$A$1:$K$167,2) -> 156 | M5: =H5/(F5^2/100) -> 0.045330813 | N5: =1/M5 -> 22.06005 | O5: =J5/100 -> 4.6
A6: 5 | B6: BC | C6: 1 | D6: BC_ACK_DSS | E6: BC_NIC_TSS | F6: 500 | G6: 117.739 | H6: 46.51 | I6: 2633 | J6: 3036 | K6: =VLOOKUP(D6,nodes!$A$1:$K$167,2) -> 2 | L6: =VLOOKUP(E6,nodes!$A$1:$K$167,2) -> 101 | M6: =H6/(F6^2/100) -> 0.018604 | N6: =1/M6 -> 53.751881 | O6: =J6/100 -> 30.36
A7: 6 | B7: BC | C7: 1 | D7: BC_ACK_DSS | E7: BC_NIC_TSS | F7: 500 | G7: 117.776 | H7: 46.52 | I7: 2073 | J7: 2842 | K7: =VLOOKUP(D7,nodes!$A$1:$K$167,2) -> 2 | L7: =VLOOKUP(E7,nodes!$A$1:$K$167,2) -> 101 | M7: =H7/(F7^2/100) -> 0.018608 | N7: =1/M7 -> 53.740327 | O7: =J7/100 -> 28.42
A8: 7 | B8: BC | C8: 1 | D8: BC_ALH_GSS | E8: BC_BTS_TSS | F8: 230 | G8: 15 | H8: 7.2 | I8: 384 | J8: 459 | K8: =VLOOKUP(D8,nodes!$A$1:$K$167,2) -> 3 | L8: =VLOOKUP(E8,nodes!$A$1:$K$167,2) -> 23 | M8: =H8/(F8^2/100) -> 0.013610586 | N8: =1/M8 -> 73.472222 | O8: =J8/100 -> 4.59
A9: 8 | B9: BC | C9: 1 | D9: BC_ALZ_DSS | E9: BC_ROS_DSS | F9: 230 | G9: 19.132 | H9: 9.18 | I9: 610 | J9: 790 | K9: =VLOOKUP(D9,nodes!$A$1:$K$167,2) -> 4 | L9: =VLOOKUP(E9,nodes!$A$1:$K$167,2) -> 118 | M9: =H9/(F9^2/100) -> 0.017353497 | N9: =1/M9 -> 57.625272 | O9: =J9/100 -> 7.9
A10: 9 | B10: BC | C10: 1 | D10: BC_ARN_DSS | E10: BC_STV_DSS | F10: 230 | G10: 12.432 | H10: 5.97 | I10: 296 | J10: 390 | K10: =VLOOKUP(D10,nodes!$A$1:$K$167,2) -> 5 | L10: =VLOOKUP(E10,nodes!$A$1:$K$167,2) -> 138 | M10: =H10/(F10^2/100) -> 0.011285444 | N10: =1/M10 -> 88.609715 | O10: =J10/100 -> 3.9
A11: 10 | B11: BC | C11: 1 | D11: BC_ARN_DSS | E11: BC_EBT_TSS | F11: 230 | G11: 67.24 | H11: 32.28 | I11: 565 | J11: 669 | K11: =VLOOKUP(D11,nodes!$A$1:$K$167,2) -> 5 | L11: =VLOOKUP(E11,nodes!$A$1:$K$167,2) -> 39 | M11: =H11/(F11^2/100) -> 0.061020794 | N11: =1/M11 -> 16.387856 | O11: =J11/100 -> 6.69
A12: 11 | B12: BC | C12: 1 | D12: BC_ASL_JCT | E12: BC_ASL_GSS | F12: 230 | G12: 2.819 | H12: 1.35 | I12: 288 | J12: 389 | K12: =VLOOKUP(D12,nodes!$A$1:$K$167,2) -> 7 | L12: =VLOOKUP(E12,nodes!$A$1:$K$167,2) -> 6 | M12: =H12/(F12^2/100) -> 0.0025519849 | N12: =1/M12 -> 391.85185 | O12: =J12/100 -> 3.89
A13: 12 | B13: BC | C13: 1 | D13: BC_ASL_JCT | E13: BC_CMS_GSS | F13: 230 | G13: 19.8 | H13: 9.5 | I13: 288 | J13: 389 | K13: =VLOOKUP(D13,nodes!$A$1:$K$167,2) -> 7 | L13: =VLOOKUP(E13,nodes!$A$1:$K$167,2) -> 30 | M13: =H13/(F13^2/100) -> 0.017958412 | N13: =1/M13 -> 55.684211 | O13: =J13/100 -> 3.89
... A253: 254 | B253: BC | C253: 1 | D253: BC_WTS_TSS | E253: BC_BTS_TSS | F253: 230 | G253: 25 | H253: 12 | I253: 402 | J253: 435 | K253: =VLOOKUP(D253,nodes!$A$1:$K$167,2) -> 166 | L253: =VLOOKUP(E253,nodes!$A$1:$K$167,2) -> 23 | M253: =H253/(F253^2/100) -> 0.02268431 | N253: =1/M253 -> 44.083333 | O253: =J253/100 -> 4.35

Sheet gen_cost
A1: gen_type | B1: gen_type_source | C1: gen_type_copper | D1: gen_type_copper_source | E1: generation_type_description | F1: generic_generation_size_MW | G1: generic_generation_size_MW_source | H1: capital_cost_CAD_per_kW | I1: total_project_cost_CAD_per_kW | J1: economic_life | K1: economic_life_source | L1: service_life | M1: service_life_source | N1: annualized_capital_cost_CAD_per_kwyear | O1: fixed_om_costs | P1: variable_om_costs | Q1: construction_time | R1: development_time | S1: average_fuel_price_CAD_per_MMBtu | T1: average_fuel_price_CAD_per_MMBtu_source | U1: carbon_emissions | V1: heat_rate | W1: heat_rate_source | X1: efficiency | Y1: efficiency_source | Z1: min_plant_load | AA1: min_plant_load_source | AB1: min_capacity_factor | AC1: min_capacity_factor_source | AD1: max_capacity_factor | AE1: max_capacity_factor_source | AF1: time_to_full_capacity | AG1: time_to_full_capacity_source | AH1: min_up_time_hours | AI1: min_up_time_hours_source | AJ1: min_down_time_hours | AK1: min_down_time_hours_source | AL1: ramp_rate_percent_per_min | AM1: ramp_rate_percent_per_min_source | AN1: spinning_reserve_capability | AO1: spinning_reserve_capability_source | AP1: forced_outage_rate | AQ1: forced_outage_rate_source | AR1: planned_outage_rate | AS1: planned_outage_rate_source | AT1: startup_cost | AU1: startup_cost_source | AV1: shutdown_cost | AW1: shutdown_cost_source | AX1: notes | AY1: notes_source
A2: biogas | B2: N/A | C2: biomass | D2: N/A | E2: biogas | F2: 36 | G2: 51 | H2: 2442.96 | I2: 3016.27 | J2: 20 | K2: 20 | L2: 40 | M2: Estimated | N2: 307.21 | O2: 31512 | P2: 9.72 | Q2: 3 | S2: 3.03 | T2: 45 | U2: 0 | V2: 8.513 | W2: 51 | X2: 0.4008 | Y2: 51 | Z2: 0.4 | AA2: 201 | AB2: 0.55 | AC2: 48 | AD2: 0.7 | AE2: 48 | AF2: 60 | AG2: 46 | AH2: 8 | AI2: Estimated | AJ2: 8 | AK2: Estimated | AL2: 0.08 | AM2: 61 | AN2: 0 | AO2: 201 | AP2: 0.09 | AQ2: Estimated | AR2: 0.08 | AS2: Estimated | AT2: 8 | AU2: 243 | AV2: 0.08 | AW2: 243 | AX2: Municipal solid waste - landfill gas | AY2: 51
A3: biomass | B3: N/A | C3: biomass | D3: N/A | E3: biomass | F3: 50 | G3: 51 | H3: 6497.4 | I3: 8109.73 | J3: 30 | K3: 237 | L3: 45 | M3: 237 | N3: 720.37 | O3: 183950 | P3: 7.07 | Q3: 4 | R3: 6 | S3: 3.03 | T3: 45 | U3: 0 | V3: 13.5 | W3: 203 | X3: 0.2527 | Y3: 203 | Z3: 0.4 | AA3: 201 | AB3: 0.6 | AC3: 48 | AD3: 0.65 | AE3: 48 | AF3: 720 | AG3: 46 | AH3: 8 | AI3: Estimated | AJ3: 8 | AK3: Estimated | AL3: 0.08 | AM3: 61 | AN3: 0.06 | AO3: 201 | AP3: 0.09 | AQ3: 203 | AR3: 0.08 | AS3: 203 | AT3: 8 | AU3: 243 | AV3: 0.08 | AW3: 243 | AX3: NULL | AY3: N/A
A4: biomass_CG | B4: N/A | C4: biomass | D4: N/A | E4: biomass cogeneration | F4: 50 | G4: 51 | H4: 6497.4 | I4: 8109.73 | J4: 30 | K4: 237 | L4: 45 | M4: 237 | N4: 720.37 | O4: 183950 | P4: 7.07 | Q4: 4 | R4: 6 | S4: 3.03 | T4: 45 | U4: 0 | V4: 13.5 | W4: 203 | X4: 0.2527 | Y4: 203 | Z4: 0.4 | AA4: 201 | AB4: 0.6 | AC4: 48 | AD4: 0.65 | AE4: 48 | AF4: 720 | AG4: 46 | AH4: 8 | AI4: Estimated | AJ4: 8 | AK4: Estimated | AL4: 0.08 | AM4: 61 | AN4: 0.06 | AO4: 201 | AP4: 0.09 | AQ4: 203 | AR4: 0.08 | AS4: 203 | AT4: 8 | AU4: 243 | AV4: 0.08 | AW4: 243 | AX4: Assumed similar operations to biomass | AY4: N/A
A5: coal | B5: N/A | C5: coal | D5: N/A | E5: coal combined cycle | F5: 650 | G5: 51 | H5: 5859.1 | I5: 7326.05 | J5: 30 | K5: 237 | L5: 45 | M5: 237 | N5: 650.75 | O5: 59384 | P5: 6.58 | Q5: 4 | R5: 6 | S5: 2.5 | T5: 50 | U5: 0.808917 | V5: 8.47 | W5: 203 | X5: 0.4028 | Y5: 203 | Z5: 0.5 | AA5: 201 | AB5: 0.4 | AC5: 47 | AD5: 0.6 | AE5: 47 | AF5: 960 | AG5: 46 | AH5: 8 | AI5: 8 | AJ5: 8 | AK5: 8 | AL5: 0.06 | AM5: 61 | AN5: 0.5 | AO5: 201 | AP5: 0.06 | AQ5: 203 | AR5: 0.12 | AS5: 203 | AT5: 165 | AU5: 202 | AV5: 1.65 | AW5: 202 | AX5: Ultra-supercritical coal USC | AY5: 51
A6: coal_CCS | B6: N/A | C6: coalCCS | D6: N/A | E6: coal carbon capture and storage | F6: 650 | G6: 51 | H6: 9514.7 | I6: 11803.62 | J6: 30 | K6: 237 | L6: 45 | M6: 237 | N6: 1048.49 | O6: 87126 | P6: 16.06 | Q6: 4 | R6: 6 | S6: 2.5 | T6: 50 | U6: 0.103455 | V6: 10.83 | W6: 203 | X6: 0.3151 | Y6: 203 | Z6: 0.5 | AA6: 201 | AB6: 0.4 | AC6: 47 | AD6: 0.6 | AE6: 47 | AF6: 960 | AG6: 46 | AH6: 8 | AI6: 8 | AJ6: 8 | AK6: 8 | AL6: 0.06 | AM6: 61 | AN6: 0.5 | AO6: 201 | AP6: 0.08 | AQ6: 203 | AR6: 0.12 | AS6: 203 | AT6: 165 | AU6: 202 | AV6: 1.65 | AW6: 202 | AX6: Ultra-supercritical coal with 90% CCS | AY6: 51
A7: diesel_CT | B7: N/A | C7: diesel | D7: N/A | E7: diesel combustion turbine | F7: 21 | G7: 51 | H7: 2912 | I7: 3476.12 | J7: 30 | K7: 237 | L7: 45 | M7: 237 | N7: 308.77 | O7: 47853 | P7: 8.32 | Q7: 2 | R7: 3 | S7: 11.9 | T7: 50 | U7: 0.515469 | V7: 8.295 | W7: 51 | X7: 0.4113 | Y7: 51 | Z7: 0.5 | AA7: 201 | AB7: 0.01 | AC7: 47 | AD7: 0.02 | AE7: 47 | AF7: 10 | AG7: 46 | AH7: 1 | AI7: 8 | AJ7: 1 | AK7: 8 | AL7: 0.2 | AM7: 61 | AN7: 0.15 | AO7: 201 | AP7: 0.09 | AQ7: Estimated | AR7: 0.08 | AS7: Estimated | AT7: 200 | AU7: Estimated | AV7: 2 | AW7: Estimated | AX7: Internal combustion engine diesel | AY7: 51
A8: diesel_ST | B8: N/A | C8: diesel | D8: N/A | E8: diesel steam turbine | F8: 21 | G8: 51 | H8: 2912 | I8: 3476.12 | J8: 30 | K8: 237 | L8: 45 | M8: 237 | N8: 308.77 | O8: 47853 | P8: 8.32 | Q8: 2 | R8: 3 | S8: 11.9 | T8: 50 | U8: 0.515469 | V8: 8.295 | W8: 51 | X8: 0.4113 | Y8: 51 | Z8: 0.5 | AA8: 201 | AB8: 0.12 | AC8: 47 | AD8: 0.15 | AE8: 47 | AF8: 960 | AG8: 46 | AH8: 4 | AI8: 8 | AJ8: 2 | AK8: 8 | AL8: 0.07 | AM8: 61 | AN8: 0.15 | AO8: 201 | AP8: 0.09 | AQ8: Estimated | AR8: 0.08 | AS8: Estimated | AT8: 200 | AU8: Estimated | AV8: 2 | AW8: Estimated | AX8: Internal combustion engine diesel | AY8: 51
A9: gasoline_CT | B9: N/A | C9: diesel | D9: N/A | E9: gasoline combustion turbine | F9: 21 | G9: 51 | H9: 2912 | I9: 3476.12 | J9: 30 | K9: 237 | L9: 45 | M9: 237 | N9: 308.77 | O9: 47853 | P9: 8.32 | Q9: 2 | R9: 3 | S9: 11.9 | T9: 50 | U9: 0.515469 | V9: 8.295 | W9: 51 | X9: 0.4113 | Y9: 51 | Z9: 0.5 | AA9: 201 | AB9: 0.01 | AC9: 47 | AD9: 0.02 | AE9: 47 | AF9: 10 | AG9: 46 | AH9: 1 | AI9: 8 | AJ9: 1 | AK9: 8 | AL9: 0.2 | AM9: 61 | AN9: 0.15 | AO9: 201 | AP9: 0.09 | AQ9: Estimated | AR9: 0.08 | AS9: Estimated | AT9: 200 | AU9: Estimated | AV9: 2 | AW9: Estimated | AX9: Internal combustion engine diesel | AY9: 51
A10: geothermal | B10: N/A | C10: geothermal | D10: N/A | E10: geothermal binary cycle | F10: 50 | G10: 51 | H10: 4423.9 | I10: 5559.93 | J10: 40 | K10: 20 | L10: 40 | M10: 20 | N10: 466.26 | O10: 200174 | P10: 1.7 | Q10: 4 | R10: 6 | S10: 0 | T10: N/A | U10: 0 | V10: 8.946 | W10: 51 | X10: 0.3814 | Y10: 51 | Z10: 0.9 | AA10: 201 | AB10: 0.68 | AC10: 48 | AD10: 0.76 | AE10: 48 | AF10: 960 | AG10: 46 | AH10: 8 | AI10: Estimated | AJ10: 8 | AK10: Estimated | AL10: 0.05 | AM10: 61 | AN10: 0.15 | AO10: 201 | AP10: 0.05 | AQ10: Estimated | AR10: 0.1 | AS10: Estimated | AT10: 0 | AU10: Estimated | AV10: 0 | AW10: Estimated | AX10: NULL | AY10: N/A
A11: h2blue_CT | B11: N/A | C11: h2blue_CT | D11: N/A | E11: hydrogen combustion turbine | F11: 105 | G11: 9 | H11: 1856.4 | I11: 2239.19 | J11: 35 | K11: 205 | L11: 45 | M11: N/A | N11: 192.13 | O11: 60263 | P11: 4.87 | Q11: 2 | R11: 3 | S11: 17.1 | T11: 9 | U11: 0.0299 | V11: 9.9 | W11: 9 | X11: 0.3446 | Y11: 9 | Z11: 0 | AA11: 201 | AB11: 0.08 | AC11: 47 | AD11: 0.15 | AE11: 47 | AF11: 10 | AG11: 46 | AH11: 1 | AI11: Estimated | AJ11: 1 | AK11: Estimated | AL11: 0.2 | AM11: 61 | AN11: 0.83 | AO11: 201 | AP11: 0.05 | AQ11: 203 | AR11: 0.07 | AS11: 203 | AT11: 90 | AU11: 202 | AV11: 0.9 | AW11: 202 | AX11: Assumptions made similar to the natural gas CT based on discussions with AESO | AY11: N/A
A12: h2green_CT | B12: N/A | C12: h2green_CT | D12: N/A | E12: hydrogen combustion turbine | F12: 105 | G12: 9 | H12: 1856.4 | I12: 2239.19 | J12: 35 | K12: 205 | L12: 45 | M12: N/A | N12: 192.13 | O12: 60263 | P12: 4.87 | Q12: 2 | R12: 3 | S12: 61.83 | T12: 9 | U12: 0 | V12: 9.9 | W12: 9 | X12: 0.3446 | Y12: 9 | Z12: 0 | AA12: 201 | AB12: 0.08 | AC12: 47 | AD12: 0.15 | AE12: 47 | AF12: 10 | AG12: 46 | AH12: 1 | AI12: Estimated | AJ12: 1 | AK12: Estimated | AL12: 0.2 | AM12: 61 | AN12: 0.83 | AO12: 201 | AP12: 0.05 | AQ12: 203 | AR12: 0.07 | AS12: 203 | AT12: 90 | AU12: 202 | AV12: 0.9 | AW12: 202 | AX12: Assumptions made similar to the natural gas CT based on discussions with AESO | AY12: N/A
A13: hydro_daily | B13: N/A | C13: hydro_daily | D13: N/A | E13: hydroelectric daily storage | F13: 100 | G13: 51 | H13: 4447.3 | I13: 5588.78 | J13: 40 | K13: 20 | L13: 80 | M13: Estimated | N13: 468.68 | O13: 115196 | P13: 5 | Q13: 4 | R13: 6 | S13: 0 | T13: N/A | U13: 0 | W13: N/A | Y13: N/A | AA13: N/A | AC13: N/A | AE13: N/A | AF13: 10 | AG13: 46 | AH13: 1 | AI13: Estimated | AJ13: 1 | AK13: Estimated | AL13: 0.15 | AM13: 61 | AN13: 0.1 | AO13: 41 | AP13: 0.05 | AQ13: 41 | AR13: 0.1 | AS13: 41 | AT13: 0 | AU13: Estimated | AV13: 0 | AW13: Estimated | AX13: Conventional hydropower | AY13: 51
A14: hydro_monthly | B14: N/A | C14: hydro_monthly | D14: N/A | E14: hydroelectric monthly storage | F14: 700 | G14: N/A | H14: 9750 | I14: 13677.91 | J14: 70 | K14: 20 | L14: 100 | M14: Estimated | N14: 1099.26 | O14: 18305 | P14: 2 | Q14: 8 | R14: 12 | S14: 0 | T14: N/A | U14: 0 | W14: N/A | Y14: N/A | AA14: N/A | AC14: N/A | AE14: N/A | AF14: 10 | AG14: 46 | AH14: 1 | AI14: Estimated | AJ14: 1 | AK14: Estimated | AL14: 0.15 | AM14: 61 | AN14: 0.2 | AO14: 41 | AP14: 0.05 | AQ14: 41 | AR14: 0.1 | AS14: 41 | AT14: 0 | AU14: Estimated | AV14: 0 | AW14: Estimated | AX14: Capital cost based on $8.7B $2021 Keeyask Project | AY14: N/A
A15: hydro_run | B15: N/A | C15: hydro_run | D15: N/A | E15: hydroelectric non-storage | F15: 65 | G15: 20 | H15: 3692 | I15: 4656.52 | J15: 40 | K15: 20 | L15: 80 | M15: Estimated | N15: 390.5 | O15: 66563 | P15: 1 | Q15: 4 | R15: 6 | S15: 0 | T15: N/A | U15: 0 | W15: N/A | Y15: N/A | AA15: N/A | AC15: N/A | AE15: N/A | AF15: 10 | AG15: 46 | AH15: 1 | AI15: Estimated | AJ15: 1 | AK15: Estimated | AM15: N/A | AN15: 0 | AO15: 41 | AP15: 0.05 | AQ15: 41 | AR15: 0.1 | AS15: 41 | AT15: 0 | AU15: Estimated | AV15: 0 | AW15: Estimated | AX15: Capital cost based on BC Hydro RODAT data | AY15: N/A
A16: MSW | B16: N/A | C16: biomass | D16: N/A | E16: municipal solid waste | F16: 50 | G16: 51 | H16: 7059 | I16: 8798.5 | J16: 30 | K16: 237 | L16: 45 | M16: 237 | N16: 781.55 | O16: 183950 | P16: 7.07 | Q16: 4 | R16: 6 | S16: 3.03 | T16: 45 | U16: 0 | V16: 13.5 | W16: 203 | X16: 0.2527 | Y16: 203 | Z16: 0.4 | AA16: 201 | AB16: 0.6 | AC16: 48 | AD16: 0.65 | AE16: 48 | AF16: 720 | AG16: 46 | AH16: 8 | AI16: Estimated | AJ16: 8 | AK16: Estimated | AL16: 0.08 | AM16: 61 | AN16: 0.06 | AO16: 201 | AP16: 0.09 | AQ16: 203 | AR16: 0.08 | AS16: 203 | AT16: 8 | AU16: 243 | AV16: 0.08 | AW16: 243 | AX16: Assumed similar operations to biomass | AY16: N/A
A17: NG_CC | B17: N/A | C17: NG_CC | D17: N/A | E17: natural gas combined cycle | F17: 1083 | G17: 51 | H17: 1528.8 | I17: 1909.29 | J17: 30 | K17: 237 | L17: 45 | M17: 237 | N17: 169.6 | O17: 17849 | P17: 2.73 | Q17: 3 | R17: 5 | S17: 3.11 | T17: 50 | U17: 0.337527 | V17: 6.36 | W17: 203 | X17: 0.5365 | Y17: 203 | Z17: 0 | AA17: 201 | AB17: 0.45 | AC17: 47 | AD17: 0.58 | AE17: 47 | AF17: 720 | AG17: 46 | AH17: 4 | AI17: 104 | AJ17: 2 | AK17: 104 | AL17: 0.08 | AM17: 61 | AN17: 0.5 | AO17: 201 | AP17: 0.05 | AQ17: 203 | AR17: 0.1 | AS17: 203 | AT17: 103 | AU17: 202 | AV17: 1.03 | AW17: 202 | AX17: Natural gas combined cycle - multi shaft | AY17: 51
A18: NG_CCS | B18: N/A | C18: NG_CCS | D18: N/A | E18: natural gas carbon capture and storage | F18: 377 | G18: 51 | H18: 4082 | I18: 4985.71 | J18: 30 | K18: 237 | L18: 45 | M18: 237 | N18: 442.87 | O18: 40378 | P18: 8.54 | Q18: 3 | R18: 5 | S18: 3.11 | T18: 50 | U18: 0.037998 | V18: 7.16 | W18: 203 | X18: 0.4765 | Y18: 203 | Z18: 0 | AA18: 201 | AB18: 0.45 | AC18: 47 | AD18: 0.58 | AE18: 47 | AF18: 720 | AG18: 46 | AH18: 4 | AI18: 104 | AJ18: 2 | AK18: 104 | AL18: 0.08 | AM18: 61 | AN18: 0.5 | AO18: 201 | AP18: 0.05 | AQ18: 203 | AR18: 0.1 | AS18: 203 | AT18: 103 | AU18: 202 | AV18: 1.03 | AW18: 202 | AX18: Natural gas combined cycle with 90% CCS | AY18: 51
A19: NG_CG | B19: N/A | C19: NG_CG | D19: N/A | E19: natural gas cogeneration | F19: 1083 | G19: 51 | H19: 1528.8 | I19: 1909.29 | J19: 30 | K19: 237 | L19: 45 | M19: 237 | N19: 169.6 | O19: 17849 | P19: 2.73 | Q19: 3 | R19: 5 | S19: 3.11 | T19: 50 | U19: 0.3375 | V19: 7.16 | W19: 203 | X19: 0.4765 | Y19: 203 | Z19: 0 | AA19: 201 | AB19: 0.45 | AC19: 47 | AD19: 0.58 | AE19: 47 | AF19: 720 | AG19: 46 | AH19: 4 | AI19: 104 | AJ19: 2 | AK19: 104 | AL19: 0.08 | AM19: 61 | AN19: 0.5 | AO19: 201 | AP19: 0.05 | AQ19: 203 | AR19: 0.1 | AS19: 203 | AT19: 103 | AU19: 202 | AV19: 1.03 | AW19: 202 | AX19: Assumed similar to costs and operations to natural gas combined cycle | AY19: N/A
A20: NG_SC | B20: N/A | C20: NG_SC | D20: N/A | E20: natural gas simple cycle | F20: 105 | G20: 51 | H20: 1856.4 | I20: 2239.19 | J20: 30 | K20: 237 | L20: 45 | M20: 237 | N20: 198.9 | O20: 23855 | P20: 6.88 | Q20: 2 | R20: 3 | S20: 3.11 | T20: 50 | U20: 0.515843 | V20: 9.72 | W20: 203 | X20: 0.351 | Y20: 203 | Z20: 0 | AA20: 201 | AB20: 0.08 | AC20: 47 | AD20: 0.15 | AE20: 47 | AF20: 10 | AG20: 46 | AH20: 1 | AI20: 104 | AJ20: 1 | AK20: 104 | AL20: 0.2 | AM20: 61 | AN20: 0.83 | AO20: 201 | AP20: 0.05 | AQ20: 203 | AR20: 0.07 | AS20: 203 | AT20: 90 | AU20: 202 | AV20: 0.9 | AW20: 202 | AX20: Combustion turbine - aeroderivative | AY20: 51
A21: nuclear | B21: N/A | C21: nuclear | D21: N/A | E21: nuclear light water reactor | F21: 2156 | G21: 51 | H21: 10110.1 | I21: 13320.33 | J21: 30 | K21: 237 | L21: 60 | M21: 237 | N21: 1183.21 | O21: 177983 | P21: 3.47 | Q21: 6 | R21: 10 | S21: 0.86 | T21: 49 | U21: 0 | V21: 10.44 | W21: 203 | X21: 0.3268 | Y21: 203 | Z21: 1 | AA21: 201 | AB21: 0.86 | AC21: 48 | AD21: 0.94 | AE21: 48 | AF21: 960 | AG21: 46 | AH21: 24 | AI21: Estimated | AJ21: 24 | AK21: Estimated | AL21: 0.02 | AM21: 61 | AN21: 0.1 | AO21: 201 | AP21: 0.03 | AQ21: 203 | AR21: 0.06 | AS21: 203 | AT21: 0 | AU21: 202 | AV21: 0 | AW21: 202 | AX21: NULL | AY21: N/A
A22: nuclear_SMR | B22: N/A | C22: nuclear_SMR | D22: N/A | E22: nuclear small modular reactor | F22: 600 | G22: 51 | H22: 10853.7 | I22: 14285.21 | J22: 30 | K22: 237 | L22: 60 | M22: 237 | N22: 1268.92 | O22: 138996 | P22: 4.39 | Q22: 6 | R22: 10 | S22: 0.86 | T22: 49 | U22: 0 | V22: 10.44 | W22: 203 | X22: 0.3268 | Y22: 203 | Z22: 1 | AA22: 201 | AB22: 0.86 | AC22: 48 | AD22: 0.94 | AE22: 48 | AF22: 960 | AG22: 46 | AH22: 24 | AI22: Estimated | AJ22: 24 | AK22: Estimated | AL22: 0.02 | AM22: 61 | AN22: 0.1 | AO22: 201 | AP22: 0.03 | AQ22: 203 | AR22: 0.06 | AS22: 203 | AT22: 0 | AU22: 202 | AV22: 0 | AW22: 202 | AX22: Assumed similar to operations to conventional nuclear | AY22: N/A
A23: oil_CT | B23: N/A | C23: diesel | D23: N/A | E23: oil combustion turbine | F23: 21 | G23: 51 | H23: 2912 | I23: 3476.12 | J23: 30 | K23: 237 | L23: 45 | M23: 237 | N23: 308.77 | O23: 51441 | P23: 8.32 | Q23: 2 | R23: 3 | S23: 11.9 | T23: 50 | U23: 0.515469 | V23: 8.295 | W23: 51 | X23: 0.4113 | Y23: 51 | Z23: 0.5 | AA23: 201 | AB23: 0.01 | AC23: 47 | AD23: 0.02 | AE23: 47 | AF23: 10 | AG23: 46 | AH23: 1 | AI23: 8 | AJ23: 1 | AK23: 8 | AL23: 0.2 | AM23: 61 | AN23: 0.15 | AO23: 201 | AP23: 0.09 | AQ23: Estimated | AR23: 0.08 | AS23: Estimated | AT23: 200 | AU23: Estimated | AV23: 2 | AW23: Estimated | AX23: Internal combustion engine diesel | AY23: 51
A24: oil_ST | B24: N/A | C24: diesel | D24: N/A | E24: oil steam turbine | F24: 21 | G24: 51 | H24: 2912 | I24: 3476.12 | J24: 30 | K24: 237 | L24: 45 | M24: 237 | N24: 308.77 | O24: 51441 | P24: 8.32 | Q24: 2 | R24: 3 | S24: 11.9 | T24: 50 | U24: 0.515469 | V24: 8.295 | W24: 51 | X24: 0.4113 | Y24: 51 | Z24: 0.5 | AA24: 201 | AB24: 0.12 | AC24: 47 | AD24: 0.15 | AE24: 47 | AF24: 960 | AG24: 46 | AH24: 4 | AI24: 8 | AJ24: 2 | AK24: 8 | AL24: 0.07 | AM24: 61 | AN24: 0.15 | AO24: 201 | AP24: 0.09 | AQ24: Estimated | AR24: 0.08 | AS24: Estimated | AT24: 200 | AU24: Estimated | AV24: 2 | AW24: Estimated | AX24: Internal combustion engine diesel | AY24: 51
A25: solar_PV | B25: N/A | C25: solar | D25: N/A | E25: solar photovoltaic | F25: 150 | G25: 51 | H25: 1882.4 | I25: 2269.77 | J25: 30 | K25: 203 | L25: 30 | M25: 203 | N25: 201.62 | O25: 22308 | P25: 0 | Q25: 2 | R25: 3 | S25: 0 | T25: N/A | U25: 0 | W25: N/A | Y25: N/A | Z25: 0 | AA25: 201 | AC25: N/A | AE25: N/A | AG25: N/A | AI25: N/A | AK25: N/A | AM25: N/A | AN25: 0 | AO25: 201 | AP25: 0 | AQ25: Estimated | AR25: 0 | AS25: Estimated | AT25: 0 | AU25: Estimated | AV25: 0 | AW25: Estimated | AX25: Costs and capacities in terms of net AC power available to the grid for the installed capacity | AY25: 51
A26: solar_recon | B26: N/A | C26: solar_recon | D26: N/A | E26: recontracted solar photovoltaic | F26: 150 | G26: 51 | H26: 1505.92 | I26: 1772.95 | J26: 30 | K26: 203 | L26: 30 | M26: 203 | N26: 157.49 | O26: 22308 | P26: 0 | Q26: 1 | R26: 2 | S26: 0 | T26: N/A | U26: 0 | W26: N/A | Y26: N/A | Z26: 0 | AA26: 201 | AC26: N/A | AE26: N/A | AG26: N/A | AI26: N/A | AK26: N/A | AM26: N/A | AN26: 0 | AO26: 201 | AP26: 0 | AQ26: Estimated | AR26: 0 | AS26: Estimated | AT26: 0 | AU26: Estimated | AV26: 0 | AW26: Estimated | AX26: 80% capital cost per MW of greenfield solar PV based on NREL data | AY26: N/A
A27: storage_lithium | B27: N/A | C27: storage_LI | D27: N/A | E27: lithium ion battery storage | F27: 50 | G27: 51 | H27: 1651 | I27: 1939.13 | J27: 15 | K27: 203 | L27: 15 | M27: 203 | N27: 226.55 | O27: 59488 | P27: 0 | Q27: 1 | R27: 1 | S27: 0 | T27: N/A | U27: 0 | W27: N/A | Y27: N/A | Z27: 0 | AA27: 201 | AB27: 0 | AC27: 205 | AD27: 0.1667 | AE27: 205 | AF27: 10 | AG27: 46 | AH27: 1 | AI27: Estimated | AJ27: 1 | AK27: Estimated | AL27: 1 | AM27: 61 | AN27: 0.5 | AO27: Estimated | AP27: 0.05 | AQ27: Estimated | AR27: 0.1 | AS27: Estimated | AT27: 0 | AU27: Estimated | AV27: 0 | AW27: Estimated | AX27: Four-hour battery storage | AY27: 51
A28: storage_pump | B28: N/A | C28: storage_PH | D28: N/A | E28: hydroelectric pumped storage | F28: 1000 | G28: 28 | H28: 4290 | I28: 5734.68 | J28: 70 | K28: 20 | L28: 100 | M28: Estimated | N28: 460.88 | O28: 15844 | P28: 1 | Q28: 6 | R28: 8 | S28: 0 | T28: N/A | U28: 0 | W28: N/A | Y28: N/A | AA28: N/A | AB28: 0 | AC28: Estimated | AD28: 0.3 | AE28: Estimated | AF28: 10 | AG28: 46 | AH28: 1 | AI28: Estimated | AJ28: 1 | AK28: Estimated | AL28: 0.15 | AM28: 61 | AN28: 0.5 | AO28: Estimated | AP28: 0.05 | AQ28: 41 | AR28: 0.1 | AS28: 41 | AT28: 0 | AU28: Estimated | AV28: 0 | AW28: Estimated | AX28: Capital cost based on $4.3B Meaford Pumped Storage Project | AY28: N/A
A29: wind_offshore | B29: N/A | C29: wind_ofs | D29: N/A | E29: offshore wind | F29: 400 | G29: 51 | H29: 8673.6 | I29: 10775.41 | J29: 30 | K29: 203 | L29: 30 | M29: 203 | N29: 957.15 | O29: 160953 | P29: 0 | Q29: 4 | R29: 6 | S29: 0 | T29: N/A | U29: 0 | W29: N/A | Y29: N/A | Z29: 0 | AA29: 201 | AC29: N/A | AE29: N/A | AG29: N/A | AI29: N/A | AK29: N/A | AM29: N/A | AN29: 0 | AO29: 201 | AP29: 0.01 | AQ29: Estimated | AR29: 0.01 | AS29: Estimated | AT29: 0 | AU29: Estimated | AV29: 0 | AW29: Estimated | AX29: TRG - 5 Mid 2021 | AY29: N/A
A30: wind_onshore | B30: N/A | C30: wind_ons | D30: N/A | E30: onshore wind | F30: 200 | G30: 51 | H30: 2727.4 | I30: 3359.17 | J30: 30 | K30: 203 | L30: 30 | M30: 203 | N30: 298.39 | O30: 38532 | P30: 0 | Q30: 3 | R30: 5 | S30: 0 | T30: N/A | U30: 0 | W30: N/A | Y30: N/A | Z30: 0 | AA30: 201 | AC30: N/A | AE30: N/A | AG30: N/A | AI30: N/A | AK30: N/A | AM30: N/A | AN30: 0 | AO30: 201 | AP30: 0.01 | AQ30: Estimated | AR30: 0.01 | AS30: Estimated | AT30: 0 | AU30: Estimated | AV30: 0 | AW30: Estimated | AX30: TRG - 5 Mid 2021 | AY30: N/A
A31: wind_recon | B31: N/A | C31: wind_recon | D31: N/A | E31: recontracted onshore wind | F31: 200 | G31: 51 | H31: 2181.92 | I31: 2621.61 | J31: 30 | K31: 203 | L31: 30 | M31: 203 | N31: 232.87 | O31: 38532 | P31: 0 | Q31: 2 | R31: 4 | S31: 0 | T31: N/A | U31: 0 | W31: N/A | Y31: N/A | Z31: 0 | AA31: 201 | AC31: N/A | AE31: N/A | AG31: N/A | AI31: N/A | AK31: N/A | AM31: N/A | AN31: 0 | AO31: 201 | AP31: 0.01 | AQ31: Estimated | AR31: 0.01 | AS31: Estimated | AT31: 0 | AU31: Estimated | AV31: 0 | AW31: Estimated | AX31: 80% capital cost per MW of greenfield onshore wind based on NREL data | AY31: N/A

Sheet economic
A1: t | B1: carbon_tax | C1: a | D1: rho_o1 | E1: rho_o2 | F1: rho_o3 | G1: rho_o4 | H1: rho_o5 | I1: rho_o6 | J1: rho_o7 | K1: rho_o8 | L1: rho_o9 | M1: rho_o10 | N1: rho_o11 | O1: rho_o12 | P1: rho_o13 | Q1: rho_o14 | R1: rho_o15 | S1: rho_o16 | T1: rho_o17 | U1: rho_o18 | V1: rho_o19 | W1: rho_o20 | X1: rho_o21 | Y1: rho_o22 | Z1: rho_o23 | AA1: rho_o24 | AB1: rho_o25 | AC1: rho_o26 | AD1: rho_o27 | AE1: rho_o28 | AF1: rho_o29 | AG1: rho_o30 | AH1: rho_o31 | AI1: rho_o32 | AJ1: rho_o33 | AK1: rho_o34 | AL1: rho_o35 | AM1: rho_o36 | AN1: rho_o37 | AO1: rho_o38 | AP1: rho_o39 | AQ1: rho_o40 | AR1: rho_o41 | AS1: rho_o42 | AT1: rho_o43 | AU1: rho_o44 | AV1: rho_o45 | AW1: rho_o46 | AX1: rho_o47 | AY1: rho_o48
A2: 1 | B2: 70.49 | C2: 0.2 | D2: =factors!C26 -> 59 | E2: =factors!D26 -> 87 | F2: =factors!E26 -> 111 | G2: =factors!F26 -> 158 | H2: =factors!G26 -> 4 | I2: =factors!H26 -> 324 | J2: =factors!I26 -> 328 | K2: =factors!J26 -> 332 | ... AY2: =factors!AX26 -> 221
A3: 2 | B3: 126.14 | C3: 0.18 | D3: =factors!C27 -> 251 | E3: =factors!D27 -> 328 | F3: =factors!E27 -> 80 | G3: =factors!F27 -> 101 | H3: =factors!G27 -> 84 | I3: =factors!H27 -> 91 | J3: =factors!I27 -> 154 | K3: =factors!J27 -> 136 | ... AY3: =factors!AX27 -> 339
A4: 3 | B4: 126.14 | C4: 0.17 | D4: =factors!C28 -> 366 | E4: =factors!D28 -> 290 | F4: =factors!E28 -> 362 | G4: =factors!F28 -> 137 | H4: =factors!G28 -> 125 | I4: =factors!H28 -> 48 | J4: =factors!I28 -> 258 | K4: =factors!J28 -> 76 | ... AY4: =factors!AX28 -> 7
A5: 4 | B5: 126.14 | C5: 0.16 | D5: =factors!C29 -> 82 | E5: =factors!D29 -> 225 | F5: =factors!E29 -> 108 | G5: =factors!F29 -> 216 | H5: =factors!G29 -> 163 | I5: =factors!H29 -> 225 | J5: =factors!I29 -> 320 | K5: =factors!J29 -> 265 | ... AY5: =factors!AX29 -> 289
A6: 5 | B6: 126.14 | C6: 0.15 | D6: =factors!C30 -> 18 | E6: =factors!D30 -> 290 | F6: =factors!E30 -> 147 | G6: =factors!F30 -> 66 | H6: =factors!G30 -> 346 | I6: =factors!H30 -> 221 | J6: =factors!I30 -> 48 | K6: =factors!J30 -> 143 | ... AY6: =factors!AX30 -> 149
A7: 6 | B7: 126.14 | C7: 0.14 | D7: =factors!C31 -> 249 | E7: =factors!D31 -> 25 | F7: =factors!E31 -> 287 | G7: =factors!F31 -> 38 | H7: =factors!G31 -> 28 | I7: =factors!H31 -> 88 | J7: =factors!I31 -> 148 | K7: =factors!J31 -> 54 | ... AY7: =factors!AX31 -> 265

Sheet demand
A1: node_code | B1: ID | C1: voltage | D1: province | E1: demand_factor | F1: Node | G1: demand_prov | H1: Load_t1_o1 | I1: Load_t1_o2 | J1: Load_t1_o3 | K1: Load_t1_o4 | L1: Load_t1_o5 | M1: Load_t1_o6 | N1: Load_t1_o7 | O1: Load_t1_o8 | P1: Load_t1_o9 | Q1: Load_t1_o10 | R1: Load_t1_o11 | S1: Load_t1_o12 | T1: Load_t1_o13 | U1: Load_t1_o14 | V1: Load_t1_o15 | W1: Load_t1_o16 | X1: Load_t1_o17 | Y1: Load_t1_o18 | Z1: Load_t1_o19 | AA1: Load_t1_o20 | AB1: Load_t1_o21 | AC1: Load_t1_o22 | AD1: Load_t1_o23 | AE1: Load_t1_o24 | AF1: Load_t1_o25 | AG1: Load_t1_o26 | AH1: Load_t1_o27 | AI1: Load_t1_o28 | AJ1: Load_t1_o29 | AK1: Load_t1_o30 | AL1: Load_t1_o31 | AM1: Load_t1_o32 | AN1: Load_t1_o33 | AO1: Load_t1_o34 | AP1: Load_t1_o35 | AQ1: Load_t1_o36 | AR1: Load_t1_o37 | AS1: Load_t1_o38 | AT1: Load_t1_o39 | AU1: Load_t1_o40 | AV1: Load_t1_o41 | AW1: Load_t1_o42 | AX1: Load_t1_o43 | AY1: Load_t1_o44 | AZ1: Load_t1_o45 | BA1: Load_t1_o46 | BB1: Load_t1_o47 | BC1: Load_t1_o48 | BD1: Load_t2_o1 | BE1: Load_t2_o2 | BF1: Load_t2_o3 | BG1: Load_t2_o4 | BH1: Load_t2_o5 | BI1: Load_t2_o6 | BJ1: Load_t2_o7 | BK1: Load_t2_o8 | BL1: Load_t2_o9 | BM1: Load_t2_o10 | BN1: Load_t2_o11 | BO1: Load_t2_o12 | BP1: Load_t2_o13 | BQ1: Load_t2_o14 | BR1: Load_t2_o15 | BS1: Load_t2_o16 | BT1: Load_t2_o17 | BU1: Load_t2_o18 | BV1: Load_t2_o19 | BW1: Load_t2_o20 | BX1: Load_t2_o21 | BY1: Load_t2_o22 | BZ1: Load_t2_o23 | CA1: Load_t2_o24 | CB1: Load_t2_o25 | CC1: Load_t2_o26 | CD1: Load_t2_o27 | CE1: Load_t2_o28 | CF1: Load_t2_o29 | CG1: Load_t2_o30 | CH1: Load_t2_o31 | CI1: Load_t2_o32 | CJ1: Load_t2_o33 | CK1: Load_t2_o34 | CL1: Load_t2_o35 | CM1: Load_t2_o36 | CN1: Load_t2_o37 | CO1: Load_t2_o38 | CP1: Load_t2_o39 | CQ1: Load_t2_o40 | CR1: Load_t2_o41 | CS1: Load_t2_o42 | CT1: Load_t2_o43 | CU1: Load_t2_o44 | CV1: Load_t2_o45 | CW1: Load_t2_o46 | CX1: Load_t2_o47 | CY1: Load_t2_o48 | CZ1: Load_t3_o1 | DA1: Load_t3_o2 | DB1: Load_t3_o3 | DC1: Load_t3_o4 | DD1: Load_t3_o5 | DE1: Load_t3_o6 | DF1: Load_t3_o7 | DG1: Load_t3_o8 | DH1: Load_t3_o9 | DI1: Load_t3_o10 | DJ1: Load_t3_o11 | DK1: Load_t3_o12 | DL1: Load_t3_o13 | DM1: Load_t3_o14 | DN1: Load_t3_o15 | DO1: Load_t3_o16 | DP1: Load_t3_o17 | DQ1: Load_t3_o18 | DR1: Load_t3_o19 | DS1: Load_t3_o20 | DT1: Load_t3_o21 | DU1: Load_t3_o22 | DV1: Load_t3_o23 | DW1: Load_t3_o24 | DX1: Load_t3_o25 | DY1: Load_t3_o26 | DZ1: Load_t3_o27 | EA1: Load_t3_o28 | EB1: Load_t3_o29 | EC1: Load_t3_o30 | ED1: Load_t3_o31 | EE1: Load_t3_o32 | EF1: Load_t3_o33 | EG1: Load_t3_o34 | EH1: Load_t3_o35 | EI1: Load_t3_o36 | EJ1: Load_t3_o37 | EK1: Load_t3_o38 | EL1: Load_t3_o39 | EM1: Load_t3_o40 | EN1: Load_t3_o41 | EO1: Load_t3_o42 | EP1: Load_t3_o43 | EQ1: Load_t3_o44 | ER1: Load_t3_o45 | ES1: Load_t3_o46 | ET1: Load_t3_o47 | EU1: Load_t3_o48 | EV1: Load_t4_o1 | EW1: Load_t4_o2 | EX1: Load_t4_o3 | EY1: Load_t4_o4 | EZ1: Load_t4_o5 | FA1: Load_t4_o6 | FB1: Load_t4_o7 | FC1: Load_t4_o8 | FD1: Load_t4_o9 | FE1: Load_t4_o10 | FF1: Load_t4_o11 | FG1: Load_t4_o12 | FH1: Load_t4_o13 | FI1: Load_t4_o14 | FJ1: Load_t4_o15 | FK1: Load_t4_o16 | FL1: Load_t4_o17 | FM1: Load_t4_o18 | FN1: Load_t4_o19 | FO1: Load_t4_o20 | FP1: Load_t4_o21 | FQ1: Load_t4_o22 | FR1: Load_t4_o23 | FS1: Load_t4_o24 | FT1: Load_t4_o25 | FU1: Load_t4_o26 | FV1: Load_t4_o27 | FW1: Load_t4_o28 | FX1: Load_t4_o29 | FY1: Load_t4_o30 | FZ1: Load_t4_o31 | GA1: Load_t4_o32 | GB1: Load_t4_o33 | GC1: Load_t4_o34 | GD1: Load_t4_o35 | GE1: Load_t4_o36 | GF1: Load_t4_o37 | GG1: Load_t4_o38 | GH1: Load_t4_o39 | GI1: Load_t4_o40 | GJ1: Load_t4_o41 | GK1: Load_t4_o42 | GL1: Load_t4_o43 | GM1: Load_t4_o44 | GN1: Load_t4_o45 | GO1: Load_t4_o46 | GP1: Load_t4_o47 | GQ1: Load_t4_o48 | GR1: Load_t5_o1 | GS1: Load_t5_o2 | GT1: Load_t5_o3 | GU1: Load_t5_o4 | GV1: Load_t5_o5 | GW1: Load_t5_o6 | GX1: Load_t5_o7 | GY1: Load_t5_o8 | GZ1: Load_t5_o9 | HA1: Load_t5_o10 | HB1: Load_t5_o11 | HC1: Load_t5_o12 | HD1: Load_t5_o13 | HE1: Load_t5_o14 | HF1: Load_t5_o15 | HG1: Load_t5_o16 | HH1: Load_t5_o17 | HI1: Load_t5_o18 | HJ1: Load_t5_o19 | HK1: Load_t5_o20 | HL1: Load_t5_o21 | HM1: Load_t5_o22 | HN1: Load_t5_o23 | HO1: Load_t5_o24 | HP1: Load_t5_o25 | HQ1: Load_t5_o26 | HR1: Load_t5_o27 | HS1: Load_t5_o28 | HT1: Load_t5_o29 | HU1: Load_t5_o30 | HV1: Load_t5_o31 | HW1: Load_t5_o32 | HX1: Load_t5_o33 | HY1: Load_t5_o34 | HZ1: Load_t5_o35 | IA1: Load_t5_o36 | IB1: Load_t5_o37 | IC1: Load_t5_o38 | ID1: Load_t5_o39 | IE1: Load_t5_o40 | IF1: Load_t5_o41 | IG1: Load_t5_o42 | IH1: Load_t5_o43 | II1: Load_t5_o44 | IJ1: Load_t5_o45 | IK1: Load_t5_o46 | IL1: Load_t5_o47 | IM1: Load_t5_o48 | IN1: Load_t6_o1 | IO1: Load_t6_o2 | IP1: Load_t6_o3 | IQ1: Load_t6_o4 | IR1: Load_t6_o5 | IS1: Load_t6_o6 | IT1: Load_t6_o7 | IU1: Load_t6_o8 | IV1: Load_t6_o9 | IW1: Load_t6_o10 | IX1: Load_t6_o11 | IY1: Load_t6_o12 | IZ1: Load_t6_o13 | JA1: Load_t6_o14 | JB1: Load_t6_o15 | JC1: Load_t6_o16 | JD1: Load_t6_o17 | JE1: Load_t6_o18 | JF1: Load_t6_o19 | JG1: Load_t6_o20 | JH1: Load_t6_o21 | JI1: Load_t6_o22 | JJ1: Load_t6_o23 | JK1: Load_t6_o24 | JL1: Load_t6_o25 | JM1: Load_t6_o26 | JN1: Load_t6_o27 | JO1: Load_t6_o28 | JP1: Load_t6_o29 | JQ1: Load_t6_o30 | JR1: Load_t6_o31 | JS1: Load_t6_o32 | JT1: Load_t6_o33 | JU1: Load_t6_o34 | JV1: Load_t6_o35 | JW1: Load_t6_o36 | JX1: Load_t6_o37 | JY1: Load_t6_o38 | JZ1: Load_t6_o39 | KA1: Load_t6_o40 | KB1: Load_t6_o41 | KC1: Load_t6_o42 | KD1: Load_t6_o43 | KE1: Load_t6_o44 | KF1: Load_t6_o45 | KG1: Load_t6_o46 | KH1: Load_t6_o47 | KI1: Load_t6_o48
A2: BC_AAL_DSS | B2: 1 | C2: 230 | D2: BC | E2: 0.003363 | F2: 1 | G2: =VLOOKUP(D2,demand_forecasted!$A$2:$G$11,2) -> 11098 | H2: =G2*E2/100 -> 0.37322574 | I2: =$H2*factors!C$3 -> 0.41316089 | J2: =$H2*factors!D$3 -> 0.39824679 | K2: =$H2*factors!E$3 -> 0.39139437 | L2: =$H2*factors!F$3 -> 0.39018512 | M2: =$H2*factors!G$3 -> 0.38978203 | N2: =$H2*factors!H$3 -> 0.40106838 | O2: =$H2*factors!I$3 -> 0.40993622 | P2: =$H2*factors!J$3 -> 0.41477323 | ... KI2: =$H2*factors!KC$3 -> 0.46025079
A3: BC_ACK_DSS | B3: 2 | C3: 230 | D3: BC | E3: 0.003918 | F3: 2 | G3: =VLOOKUP(D3,demand_forecasted!$A$2:$G$11,2) -> 11098 | H3: =G3*E3/100 -> 0.43481964 | I3: =$H3*factors!C$3 -> 0.48134534 | J3: =$H3*factors!D$3 -> 0.46396995 | K3: =$H3*factors!E$3 -> 0.45598666 | L3: =$H3*factors!F$3 -> 0.45457784 | M3: =$H3*factors!G$3 -> 0.45410824 | N3: =$H3*factors!H$3 -> 0.46725719 | O3: =$H3*factors!I$3 -> 0.4775885 | P3: =$H3*factors!J$3 -> 0.48322376 | ... KI3: =$H3*factors!KC$3 -> 0.53620654
A4: BC_ALH_GSS | B4: 3 | C4: 230 | D4: BC | E4: 0.003363 | F4: 3 | G4: =VLOOKUP(D4,demand_forecasted!$A$2:$G$11,2) -> 11098 | H4: =G4*E4/100 -> 0.37322574 | I4: =$H4*factors!C$3 -> 0.41316089 | J4: =$H4*factors!D$3 -> 0.39824679 | K4: =$H4*factors!E$3 -> 0.39139437 | L4: =$H4*factors!F$3 -> 0.39018512 | M4: =$H4*factors!G$3 -> 0.38978203 | N4: =$H4*factors!H$3 -> 0.40106838 | O4: =$H4*factors!I$3 -> 0.40993622 | P4: =$H4*factors!J$3 -> 0.41477323 | ... KI4: =$H4*factors!KC$3 -> 0.46025079
A5: BC_ALZ_DSS | B5: 4 | C5: 230 | D5: BC | E5: 0.006494 | F5: 4 | G5: =VLOOKUP(D5,demand_forecasted!$A$2:$G$11,2) -> 11098 | H5: =G5*E5/100 -> 0.72070412 | I5: =$H5*factors!C$3 -> 0.79781946 | J5: =$H5*factors!D$3 -> 0.76902012 | K5: =$H5*factors!E$3 -> 0.755788 | L5: =$H5*factors!F$3 -> 0.75345292 | M5: =$H5*factors!G$3 -> 0.75267455 | N5: =$H5*factors!H$3 -> 0.77446865 | O5: =$H5*factors!I$3 -> 0.79159258 | P5: =$H5*factors!J$3 -> 0.8009329 | ... KI5: =$H5*factors!KC$3 -> 0.8887507
A6: BC_ARN_DSS | B6: 5 | C6: 230 | D6: BC | E6: 0.015035 | F6: 5 | G6: =VLOOKUP(D6,demand_forecasted!$A$2:$G$11,2) -> 11098 | H6: =G6*E6/100 -> 1.6685843 | I6: =$H6*factors!C$3 -> 1.8471228 | J6: =$H6*factors!D$3 -> 1.7804462 | K6: =$H6*factors!E$3 -> 1.749811 | L6: =$H6*factors!F$3 -> 1.7444048 | M6: =$H6*factors!G$3 -> 1.7426027 | N6: =$H6*factors!H$3 -> 1.7930607 | O6: =$H6*factors!I$3 -> 1.8327063 | P6: =$H6*factors!J$3 -> 1.8543311 | ... KI6: =$H6*factors!KC$3 -> 2.0576481
A7: BC_ASL_GSS | B7: 6 | C7: 230 | D7: BC | E7: 0.003087 | F7: 6 | G7: =VLOOKUP(D7,demand_forecasted!$A$2:$G$11,2) -> 11098 | H7: =G7*E7/100 -> 0.34259526 | I7: =$H7*factors!C$3 -> 0.37925295 | J7: =$H7*factors!D$3 -> 0.36556285 | K7: =$H7*factors!E$3 -> 0.3592728 | L7: =$H7*factors!F$3 -> 0.35816279 | M7: =$H7*factors!G$3 -> 0.35779279 | N7: =$H7*factors!H$3 -> 0.36815287 | O7: =$H7*factors!I$3 -> 0.37629293 | P7: =$H7*factors!J$3 -> 0.38073296 | ... KI7: =$H7*factors!KC$3 -> 0.4224782
A8: BC_ASL_JCT | B8: 7 | C8: 230 | D8: BC | E8: 0.003087 | F8: 7 | G8: =VLOOKUP(D8,demand_forecasted!$A$2:$G$11,2) -> 11098 | H8: =G8*E8/100 -> 0.34259526 | I8: =$H8*factors!C$3 -> 0.37925295 | J8: =$H8*factors!D$3 -> 0.36556285 | K8: =$H8*factors!E$3 -> 0.3592728 | L8: =$H8*factors!F$3 -> 0.35816279 | M8: =$H8*factors!G$3 -> 0.35779279 | N8: =$H8*factors!H$3 -> 0.36815287 | O8: =$H8*factors!I$3 -> 0.37629293 | P8: =$H8*factors!J$3 -> 0.38073296 | ... KI8: =$H8*factors!KC$3 -> 0.4224782
A9: BC_BCR_ISS | B9: 8 | C9: 230 | D9: BC | E9: 0.003341 | F9: 8 | G9: =VLOOKUP(D9,demand_forecasted!$A$2:$G$11,2) -> 11098 | H9: =G9*E9/100 -> 0.37078418 | I9: =$H9*factors!C$3 -> 0.41045809 | J9: =$H9*factors!D$3 -> 0.39564155 | K9: =$H9*factors!E$3 -> 0.38883395 | L9: =$H9*factors!F$3 -> 0.38763261 | M9: =$H9*factors!G$3 -> 0.38723217 | N9: =$H9*factors!H$3 -> 0.39844468 | O9: =$H9*factors!I$3 -> 0.40725451 | P9: =$H9*factors!J$3 -> 0.41205987 | ... KI9: =$H9*factors!KC$3 -> 0.45723993
A10: BC_BDH_GSS | B10: 9 | C10: 230 | D10: BC | E10: 0.003087 | F10: 9 | G10: =VLOOKUP(D10,demand_forecasted!$A$2:$G$11,2) -> 11098 | H10: =G10*E10/100 -> 0.34259526 | I10: =$H10*factors!C$3 -> 0.37925295 | J10: =$H10*factors!D$3 -> 0.36556285 | K10: =$H10*factors!E$3 -> 0.3592728 | L10: =$H10*factors!F$3 -> 0.35816279 | M10: =$H10*factors!G$3 -> 0.35779279 | N10: =$H10*factors!H$3 -> 0.36815287 | O10: =$H10*factors!I$3 -> 0.37629293 | P10: =$H10*factors!J$3 -> 0.38073296 | ... KI10: =$H10*factors!KC$3 -> 0.4224782
A11: BC_BDH_JCT | B11: 10 | C11: 230 | D11: BC | E11: 0.003087 | F11: 10 | G11: =VLOOKUP(D11,demand_forecasted!$A$2:$G$11,2) -> 11098 | H11: =G11*E11/100 -> 0.34259526 | I11: =$H11*factors!C$3 -> 0.37925295 | J11: =$H11*factors!D$3 -> 0.36556285 | K11: =$H11*factors!E$3 -> 0.3592728 | L11: =$H11*factors!F$3 -> 0.35816279 | M11: =$H11*factors!G$3 -> 0.35779279 | N11: =$H11*factors!H$3 -> 0.36815287 | O11: =$H11*factors!I$3 -> 0.37629293 | P11: =$H11*factors!J$3 -> 0.38073296 | ... KI11: =$H11*factors!KC$3 -> 0.4224782
A12: BC_BEN_TSS | B12: 11 | C12: 230 | D12: BC | E12: 0.003893 | F12: 11 | G12: =VLOOKUP(D12,demand_forecasted!$A$2:$G$11,2) -> 11098 | H12: =G12*E12/100 -> 0.43204514 | I12: =$H12*factors!C$3 -> 0.47827397 | J12: =$H12*factors!D$3 -> 0.46100945 | K12: =$H12*factors!E$3 -> 0.4530771 | L12: =$H12*factors!F$3 -> 0.45167727 | M12: =$H12*factors!G$3 -> 0.45121066 | N12: =$H12*factors!H$3 -> 0.46427571 | O12: =$H12*factors!I$3 -> 0.4745411 | P12: =$H12*factors!J$3 -> 0.4801404 | ... KI12: =$H12*factors!KC$3 -> 0.53278511
A13: BC_BLM_DSS | B13: 12 | C13: 230 | D13: BC | E13: 0.003341 | F13: 12 | G13: =VLOOKUP(D13,demand_forecasted!$A$2:$G$11,2) -> 11098 | H13: =G13*E13/100 -> 0.37078418 | I13: =$H13*factors!C$3 -> 0.41045809 | J13: =$H13*factors!D$3 -> 0.39564155 | K13: =$H13*factors!E$3 -> 0.38883395 | L13: =$H13*factors!F$3 -> 0.38763261 | M13: =$H13*factors!G$3 -> 0.38723217 | N13: =$H13*factors!H$3 -> 0.39844468 | O13: =$H13*factors!I$3 -> 0.40725451 | P13: =$H13*factors!J$3 -> 0.41205987 | ... KI13: =$H13*factors!KC$3 -> 0.45723993
... A167: BC_WTS_TSS | B167: 166 | C167: 230 | D167: BC | E167: 0.002609 | F167: 166 | G167: =VLOOKUP(D167,demand_forecasted!$A$2:$G$11,2) -> 11098 | H167: =G167*E167/100 -> 0.28954682 | I167: =$H167*factors!C$3 -> 0.32052833 | J167: =$H167*factors!D$3 -> 0.30895804 | K167: =$H167*factors!E$3 -> 0.30364196 | L167: =$H167*factors!F$3 -> 0.30270383 | M167: =$H167*factors!G$3 -> 0.30239112 | N167: =$H167*factors!H$3 -> 0.31114701 | O167: =$H167*factors!I$3 -> 0.31802665 | P167: =$H167*factors!J$3 -> 0.32177917 | ... KI167: =$H167*factors!KC$3 -> 0.35706045

Sheet demand_forecasted
A1: ID | B1: year_2025 | C1: year_2030 | D1: year_2035 | E1: year_2040 | F1: year_2045 | G1: year_2050
A2: AB | B2: 12411 | C2: 12759 | D2: 13470 | E2: 14839 | F2: 16760 | G2: 18636
A3: BC | B3: 11098 | C3: 11290 | D3: 11780 | E3: 12360 | F3: 12932 | G3: 13531
A4: MB | B4: 5051 | C4: 5316 | D4: 5651 | E4: 6116 | F4: 6914 | G4: 7746
A5: NB | B5: 3240 | C5: 3270 | D5: 3333 | E5: 3401 | F5: 3469 | G5: 3539
A6: NL | B6: 2058 | C6: 2359 | D6: 2612 | E6: 2937 | F6: 3303 | G6: 3715
A7: NS | B7: 2408 | C7: 2547 | D7: 2766 | E7: 2970 | F7: 3190 | G7: 3425
A8: ON | B8: 24640 | C8: 26940 | D8: 29650 | E8: 31900 | F8: 33540 | G8: 35480
A9: PE | B9: 337 | C9: 374 | D9: 422 | E9: 476 | F9: 537 | G9: 605
A10: QC | B10: 40535 | C10: 42627 | D10: 44983 | E10: 47214 | F10: 49555 | G10: 52012
A11: SK | B11: 4225 | C11: 4457 | D11: 4730 | E11: 4998 | F11: 5285 | G11: 5589

Sheet factors
C1: Operating conditions
A2: Year | C2: 1 | D2: 2 | E2: 3 | F2: 4 | G2: 5 | H2: 6 | I2: 7 | J2: 8 | K2: 9 | L2: 10 | M2: 11 | N2: 12 | O2: 13 | P2: 14 | Q2: 15 | R2: 16 | S2: 17 | T2: 18 | U2: 19 | V2: 20 | W2: 21 | X2: 22 | Y2: 23 | Z2: 24 | AA2: 25 | AB2: 26 | AC2: 27 | AD2: 28 | AE2: 29 | AF2: 30 | AG2: 31 | AH2: 32 | AI2: 33 | AJ2: 34 | AK2: 35 | AL2: 36 | AM2: 37 | AN2: 38 | AO2: 39 | AP2: 40 | AQ2: 41 | AR2: 42 | AS2: 43 | AT2: 44 | AU2: 45 | AV2: 46 | AW2: 47 | AX2: 48
A3: 1 | B3: 1 | C3: 1.107 | D3: 1.06704 | E3: 1.04868 | F3: 1.04544 | G3: 1.04436 | H3: 1.0746 | I3: 1.09836 | J3: 1.11132 | K3: 1.04328 | L3: 1.026 | M3: 1.06812 | N3: 1.10484 | O3: 1.04652 | P3: 1.08864 | Q3: 1.09836 | R3: 1.05084 | S3: 1.04112 | T3: 1.1232 | U3: 1.06056 | V3: 1.06164 | W3: 1.06272 | X3: 1.04004 | Y3: 1.04868 | Z3: 1.07028 | AA3: 1.04328 | AB3: 1.03896 | AC3: 1.07244 | AD3: 1.11348 | AE3: 1.07136 | AF3: 1.02924 | AG3: 1.0584 | AH3: 1.04112 | AI3: 1.0908 | AJ3: 1.04544 | AK3: 1.07892 | AL3: 1.05516 | AM3: 1.02924 | AN3: 1.06164 | AO3: 1.12428 | AP3: 1.06272 | AQ3: 1.05192 | AR3: 1.1124 | AS3: 1.026 | AT3: 1.09944 | AU3: 1.07568 | AV3: 1.06164 | AW3: 1.1232 | AX3: 1.0368 | AY3: 1.21894 | AZ3: 1.13516 | BA3: 1.15168 | BB3: 1.16702 | BC3: 1.2095 | BD3: 1.15522 | BE3: 1.15758 | BF3: 1.1446 | BG3: 1.22248 | BH3: 1.20714 | BI3: 1.13516 | BJ3: 1.13162 | BK3: 1.1505 | BL3: 1.1918 | BM3: 1.21068 | BN3: 1.21422 | BO3: 1.23428 | BP3: 1.14814 | BQ3: 1.1741 | BR3: 1.15168 | BS3: 1.20478 | BT3: 1.18236 | BU3: 1.16702 | BV3: 1.12926 | BW3: 1.1623 | BX3: 1.16584 | BY3: 1.18236 | BZ3: 1.16466 | CA3: 1.12572 | CB3: 1.1269 | CC3: 1.121 | CD3: 1.16702 | CE3: 1.21894 | CF3: 1.14224 | CG3: 1.16938 | CH3: 1.13044 | CI3: 1.1387 | CJ3: 1.19298 | CK3: 1.15758 | CL3: 1.19416 | CM3: 1.23192 | CN3: 1.21776 | CO3: 1.19062 | CP3: 1.239 | CQ3: 1.17174 | CR3: 1.15404 | CS3: 1.14342 | CT3: 1.1269 | CU3: 1.17 | CV3: 1.2456 | CW3: 1.1928 | CX3: 1.1844 | CY3: 1.2192 | CZ3: 1.2168 | DA3: 1.212 | DB3: 1.212 | DC3: 1.1664 | DD3: 1.236 | DE3: 1.236 | DF3: 1.2216 | DG3: 1.1508 | DH3: 1.2072 | DI3: 1.2468 | DJ3: 1.236 | DK3: 1.1784 | DL3: 1.1652 | DM3: 1.2588 | DN3: 1.1832 | DO3: 1.2384 | DP3: 1.2096 | DQ3: 1.1544 | DR3: 1.2228 | DS3: 1.1604 | DT3: 1.2408 | DU3: 1.1688 | DV3: 1.14 | DW3: 1.2264 | DX3: 1.1508 | DY3: 1.1604 | DZ3: 1.2588 | EA3: 1.176 | EB3: 1.1796 | EC3: 1.1772 | ED3: 1.1472 | EE3: 1.2264 | EF3: 1.1664 | EG3: 1.2132 | EH3: 1.14 | EI3: 1.1568 | EJ3: 1.2204 | EK3: 1.1868 | EL3: 1.236 | EM3: 1.2204 | EN3: 1.248 | EO3: 1.26 | EP3: 1.1808 | EQ3: 1.29875 | ER3: 1.285 | ES3: 1.31125 | ET3: 1.29875 | EU3: 1.19375 | EV3: 1.2475 | EW3: 1.2825 | EX3: 1.2375 | EY3: 1.30375 | EZ3: 1.305 | FA3: 1.19375 | FB3: 1.25625 | FC3: 1.30875 | FD3: 1.25625 | FE3: 1.2775 | FF3: 1.28125 | FG3: 1.295 | FH3: 1.21125 | FI3: 1.28625 | FJ3: 1.25 | FK3: 1.2375 | FL3: 1.2625 | FM3: 1.255 | FN3: 1.2825 | FO3: 1.2325 | FP3: 1.2225 | FQ3: 1.30875 | FR3: 1.285 | FS3: 1.25875 | FT3: 1.19625 | FU3: 1.25875 | FV3: 1.305 | FW3: 1.2225 | FX3: 1.24375 | FY3: 1.24375 | FZ3: 1.24 | GA3: 1.19125 | GB3: 1.2675 | GC3: 1.18875 | GD3: 1.19125 | GE3: 1.22125 | GF3: 1.29375 | GG3: 1.22625 | GH3: 1.265 | GI3: 1.195 | GJ3: 1.28125 | GK3: 1.3075 | GL3: 1.2825 | GM3: 1.21285 | GN3: 1.24079 | GO3: 1.27 | GP3: 1.2192 | GQ3: 1.26238 | GR3: 1.24206 | GS3: 1.23571 | GT3: 1.28143 | GU3: 1.23952 | GV3: 1.28143 | GW3: 1.24968 | GX3: 1.28651 | GY3: 1.27 | GZ3: 1.30937 | HA3: 1.25857 | HB3: 1.24206 | HC3: 1.22682 | HD3: 1.21285 | HE3: 1.2827 | HF3: 1.20904 | HG3: 1.22174 | HH3: 1.30302 | HI3: 1.24968 | HJ3: 1.3335 | HK3: 1.2192 | HL3: 1.29286 | HM3: 1.31572 | HN3: 1.22682 | HO3: 1.23952 | HP3: 1.25476 | HQ3: 1.27254 | HR3: 1.32461 | HS3: 1.25857 | HT3: 1.30683 | HU3: 1.24333 | HV3: 1.28651 | HW3: 1.29921 | HX3: 1.2065 | HY3: 1.28143 | HZ3: 1.27381 | IA3: 1.26238 | IB3: 1.30937 | IC3: 1.25349 | ID3: 1.26492 | IE3: 1.31064 | IF3: 1.25476 | IG3: 1.24333 | IH3: 1.25095 | II3: 1.26365 | IJ3: 1.22174 | IK3: 1.21793 | IL3: 1.25349 | IM3: 1.26365 | IN3: 1.27254 | IO3: 1.30048 | IP3: 1.31699 | IQ3: 1.2446 | IR3: 1.30048 | IS3: 1.28143 | IT3: 1.30302 | IU3: 1.23063 | IV3: 1.25349 | IW3: 1.22428 | IX3: 1.3335 | IY3: 1.22809 | IZ3: 1.28905 | JA3: 1.26619 | JB3: 1.29032 | JC3: 1.20777 | JD3: 1.30048 | JE3: 1.25857 | JF3: 1.30937 | JG3: 1.22174 | JH3: 1.22174 | JI3: 1.2065 | JJ3: 1.30429 | JK3: 1.27127 | JL3: 1.3208 | JM3: 1.2065 | JN3: 1.26746 | JO3: 1.22555 | JP3: 1.24587 | JQ3: 1.33096 | JR3: 1.31826 | JS3: 1.24079 | JT3: 1.25476 | JU3: 1.25984 | JV3: 1.21793 | JW3: 1.22428 | JX3: 1.22555 | JY3: 1.30429 | JZ3: 1.31953 | KA3: 1.27254 | KB3: 1.2446 | KC3: 1.23317 | KD3: 1.2065 | KE3: 1.28904 | KF3: 1.37288 | KG3: 1.31655 | KH3: 1.31655 | KI3: 1.27856 | KJ3: 1.32965 | KK3: 1.31131 | KL3: 1.26415 | KM3: 1.32179 | KN3: 1.3231 | KO3: 1.24974 | KP3: 1.29821 | KQ3: 1.35454 | KR3: 1.33751 | KS3: 1.31786 | KT3: 1.28249 | KU3: 1.25629 | KV3: 1.32703 | KW3: 1.31 | KX3: 1.30214 | KY3: 1.26415 | KZ3: 1.24974 | LA3: 1.3755 | LB3: 1.37419 | LC3: 1.33358 | LD3: 1.29821 | LE3: 1.31393 | LF3: 1.37157 | LG3: 1.37157 | LH3: 1.27856 | LI3: 1.28904 | LJ3: 1.32834 | LK3: 1.34013 | LL3: 1.25498 | LM3: 1.26022 | LN3: 1.36764 | LO3: 1.25105 | LP3: 1.24974 | LQ3: 1.24581 | LR3: 1.31 | LS3: 1.30476 | LT3: 1.30869 | LU3: 1.36502 | LV3: 1.28118 | LW3: 1.25891 | LX3: 1.2969 | LY3: 1.31786 | LZ3: 1.34406 | MA3: 1.3002 | MB3: 1.25532 | MC3: 1.3266 | MD3: 1.36752 | ME3: 1.2672 | MF3: 1.35432 | MG3: 1.33188 | MH3: 1.26984 | MI3: 1.33056 | MJ3: 1.25532 | MK3: 1.37148 | ML3: 1.32924 | MM3: 1.33716 | MN3: 1.353 | MO3: 1.35696 | MP3: 1.25532 | MQ3: 1.32792 | MR3: 1.3728 | MS3: 1.26324 | MT3: 1.38336 | MU3: 1.34508 | MV3: 1.35168 | MW3: 1.36488 | MX3: 1.30152 | MY3: 1.2804 | MZ3: 1.36884 | NA3: 1.34508 | NB3: 1.37544 | NC3: 1.28568 | ND3: 1.35036 | NE3: 1.3464 | NF3: 1.29096 | NG3: 1.38072 | NH3: 1.27644 | NI3: 1.3398 | NJ3: 1.34376 | NK3: 1.28964 | NL3: 1.28172 | NM3: 1.3728 | NN3: 1.34112 | NO3: 1.25796 | NP3: 1.38468 | NQ3: 1.30548 | NR3: 1.37544 | NS3: 1.3662 | NT3: 1.33452 | NU3: 1.37808 | NV3: 1.3794 | NW3: 1.3731 | NX3: 1.43934 | NY3: 1.36068 | NZ3: 1.38966 | OA3: 1.41864 | OB3: 1.32342 | OC3: 1.34964 | OD3: 1.3593 | OE3: 1.37724 | OF3: 1.41312 | OG3: 1.37448 | OH3: 1.4076 | OI3: 1.449 | OJ3: 1.40208 | OK3: 1.3386 | OL3: 1.34688 | OM3: 1.4145 | ON3: 1.3938 | OO3: 1.38966 | OP3: 1.4421 | OQ3: 1.43658 | OR3: 1.31238 | OS3: 1.42278 | OT3: 1.35102 | OU3: 1.43106 | OV3: 1.33032 | OW3: 1.3386 | OX3: 1.32756 | OY3: 1.3593 | OZ3: 1.3386 | PA3: 1.44762 | PB3: 1.41726 | PC3: 1.32342 | PD3: 1.38138 | PE3: 1.32756 | PF3: 1.4007 | PG3: 1.39242 | PH3: 1.39794 | PI3: 1.36482 | PJ3: 1.42968 | PK3: 1.36068 | PL3: 1.3593 | PM3: 1.44348 | PN3: 1.3593 | PO3: 1.3593 | PP3: 1.33308 | PQ3: 1.32066 | PR3: 1.42692 | PS3: 1.404 | PT3: 1.42848 | PU3: 1.44144 | PV3: 1.41408 | PW3: 1.45296 | PX3: 1.40256 | PY3: 1.37088 | PZ3: 1.47744 | QA3: 1.50192 | QB3: 1.44432 | QC3: 1.41408 | QD3: 1.47312 | QE3: 1.476 | QF3: 1.42272 | QG3: 1.38672 | QH3: 1.44432 | QI3: 1.47744 | QJ3: 1.43424 | QK3: 1.4328 | QL3: 1.48464 | QM3: 1.4904 | QN3: 1.40688 | QO3: 1.4832 | QP3: 1.49328 | QQ3: 1.43568 | QR3: 1.3896 | QS3: 1.50336 | QT3: 1.50624 | QU3: 1.48032 | QV3: 1.49328 | QW3: 1.43568 | QX3: 1.3824 | QY3: 1.45152 | QZ3: 1.46016 | RA3: 1.40256 | RB3: 1.36944 | RC3: 1.43856 | RD3: 1.37808 | RE3: 1.46736 | RF3: 1.43856 | RG3: 1.45728 | RH3: 1.40544 | RI3: 1.39104 | RJ3: 1.40544 | RK3: 1.41696 | RL3: 1.3968 | RM3: 1.3896 | RN3: 1.42704
A4: 2 | B4: 1.0524649
A5: 3 | B5: 1.1187884
A6: 4 | B6: 1.2108493
A7: 5 | B7: 1.3688379
A8: 6 | B8: 1.5335577
A13: Year
A14: 1 | C14: 15 | D14: 22 | E14: 28 | F14: 40 | G14: 1 | H14: 82 | I14: 83 | J14: 84 | K14: 94 | L14: 25 | M14: 85 | N14: 20 | O14: 13 | P14: 22 | Q14: 71 | R14: 40 | S14: 32 | T14: 84 | U14: 88 | V14: 3 | W14: 17 | X14: 13 | Y14: 32 | Z14: 99 | AA14: 45 | AB14: 79 | AC14: 10 | AD14: 17 | AE14: 86 | AF14: 26 | AG14: 96 | AH14: 20 | AI14: 73 | AJ14: 1 | AK14: 46 | AL14: 57 | AM14: 47 | AN14: 12 | AO14: 42 | AP14: 47 | AQ14: 80 | AR14: 83 | AS14: 1 | AT14: 51 | AU14: 6 | AV14: 87 | AW14: 56 | AX14: 56
A15: 2 | C15: 72 | D15: 94 | E15: 23 | F15: 29 | G15: 24 | H15: 26 | I15: 44 | J15: 39 | K15: 72 | L15: 3 | M15: 25 | N15: 73 | O15: 70 | P15: 78 | Q15: 74 | R15: 65 | S15: 46 | T15: 74 | U15: 65 | V15: 96 | W15: 79 | X15: 76 | Y15: 36 | Z15: 47 | AA15: 57 | AB15: 75 | AC15: 41 | AD15: 47 | AE15: 49 | AF15: 2 | AG15: 81 | AH15: 22 | AI15: 92 | AJ15: 47 | AK15: 43 | AL15: 43 | AM15: 2 | AN15: 56 | AO15: 2 | AP15: 81 | AQ15: 63 | AR15: 23 | AS15: 21 | AT15: 40 | AU15: 87 | AV15: 71 | AW15: 38 | AX15: 98
A16: 3 | C16: 91 | D16: 72 | E16: 90 | F16: 34 | G16: 31 | H16: 12 | I16: 64 | J16: 19 | K16: 6 | L16: 55 | M16: 23 | N16: 45 | O16: 54 | P16: 51 | Q16: 57 | R16: 13 | S16: 37 | T16: 93 | U16: 2 | V16: 60 | W16: 91 | X16: 50 | Y16: 86 | Z16: 7 | AA16: 15 | AB16: 46 | AC16: 79 | AD16: 64 | AE16: 85 | AF16: 3 | AG16: 10 | AH16: 91 | AI16: 37 | AJ16: 16 | AK16: 39 | AL16: 12 | AM16: 8 | AN16: 31 | AO16: 52 | AP16: 97 | AQ16: 79 | AR16: 67 | AS16: 25 | AT16: 33 | AU16: 46 | AV16: 42 | AW16: 56 | AX16: 1
A17: 4 | C17: 25 | D17: 69 | E17: 33 | F17: 66 | G17: 50 | H17: 69 | I17: 98 | J17: 81 | K17: 22 | L17: 10 | M17: 95 | N17: 22 | O17: 19 | P17: 96 | Q17: 59 | R17: 25 | S17: 60 | T17: 64 | U17: 83 | V17: 66 | W17: 39 | X17: 84 | Y17: 45 | Z17: 93 | AA17: 98 | AB17: 92 | AC17: 13 | AD17: 99 | AE17: 82 | AF17: 99 | AG17: 38 | AH17: 4 | AI17: 43 | AJ17: 41 | AK17: 81 | AL17: 2 | AM17: 31 | AN17: 61 | AO17: 82 | AP17: 40 | AQ17: 23 | AR17: 27 | AS17: 49 | AT17: 73 | AU17: 49 | AV17: 88 | AW17: 5 | AX17: 88
A18: 5 | C18: 5 | D18: 79 | E18: 40 | F18: 18 | G18: 94 | H18: 60 | I18: 13 | J18: 39 | K18: 56 | L18: 45 | M18: 55 | N18: 93 | O18: 13 | P18: 63 | Q18: 84 | R18: 52 | S18: 20 | T18: 19 | U18: 5 | V18: 35 | W18: 52 | X18: 42 | Y18: 43 | Z18: 89 | AA18: 42 | AB18: 4 | AC18: 81 | AD18: 28 | AE18: 35 | AF18: 37 | AG18: 90 | AH18: 97 | AI18: 12 | AJ18: 46 | AK18: 1 | AL18: 58 | AM18: 63 | AN18: 39 | AO18: 65 | AP18: 78 | AQ18: 48 | AR18: 77 | AS18: 70 | AT18: 56 | AU18: 91 | AV18: 50 | AW18: 60 | AX18: 41
A19: 6 | C19: 79 | D19: 8 | E19: 91 | F19: 12 | G19: 9 | H19: 28 | I19: 47 | J19: 17 | K19: 51 | L19: 79 | M19: 9 | N19: 98 | O19: 45 | P19: 99 | Q19: 67 | R19: 63 | S19: 50 | T19: 74 | U19: 32 | V19: 30 | W19: 92 | X19: 93 | Y19: 41 | Z19: 76 | AA19: 14 | AB19: 51 | AC19: 87 | AD19: 45 | AE19: 98 | AF19: 10 | AG19: 76 | AH19: 57 | AI19: 37 | AJ19: 97 | AK19: 18 | AL19: 96 | AM19: 80 | AN19: 60 | AO19: 46 | AP19: 91 | AQ19: 53 | AR19: 27 | AS19: 96 | AT19: 3 | AU19: 97 | AV19: 74 | AW19: 91 | AX19: 85
A20: 7 | C20: 49 | D20: 57 | E20: 78 | F20: 68 | G20: 100 | H20: 12 | I20: 64 | J20: 26 | K20: 63 | L20: 24 | M20: 6 | N20: 96 | O20: 85 | P20: 9 | Q20: 1 | R20: 19 | S20: 71 | T20: 68 | U20: 86 | V20: 83 | W20: 58 | X20: 49 | Y20: 39 | Z20: 29 | AA20: 54 | AB20: 23 | AC20: 9 | AD20: 32 | AE20: 77 | AF20: 4 | AG20: 85 | AH20: 97 | AI20: 19 | AJ20: 44 | AK20: 33 | AL20: 98 | AM20: 93 | AN20: 61 | AO20: 62 | AP20: 52 | AQ20: 31 | AR20: 13 | AS20: 7 | AT20: 24 | AU20: 45 | AV20: 74 | AW20: 7 | AX20: 51
A21: 8 | C21: 47 | D21: 83 | E21: 72 | F21: 60 | G21: 23 | H21: 85 | I21: 23 | J21: 2 | K21: 42 | L21: 51 | M21: 45 | N21: 15 | O21: 41 | P21: 33 | Q21: 3 | R21: 92 | S21: 31 | T21: 57 | U21: 61 | V21: 66 | W21: 25 | X21: 79 | Y21: 54 | Z21: 61 | AA21: 41 | AB21: 94 | AC21: 54 | AD21: 76 | AE21: 56 | AF21: 44 | AG21: 49 | AH21: 83 | AI21: 1 | AJ21: 84 | AK21: 57 | AL21: 82 | AM21: 21 | AN21: 73 | AO21: 100 | AP21: 57 | AQ21: 8 | AR21: 10 | AS21: 23 | AT21: 69 | AU21: 74 | AV21: 26 | AW21: 15 | AX21: 15
A22: 9 | C22: 11 | D22: 65 | E22: 32 | F22: 95 | G22: 5 | H22: 76 | I22: 26 | J22: 72 | K22: 42 | L22: 91 | M22: 75 | N22: 21 | O22: 93 | P22: 65 | Q22: 90 | R22: 28 | S22: 98 | T22: 74 | U22: 30 | V22: 91 | W22: 89 | X22: 66 | Y22: 84 | Z22: 23 | AA22: 7 | AB22: 42 | AC22: 39 | AD22: 78 | AE22: 81 | AF22: 90 | AG22: 7 | AH22: 43 | AI22: 15 | AJ22: 82 | AK22: 81 | AL22: 4 | AM22: 56 | AN22: 74 | AO22: 20 | AP22: 54 | AQ22: 17 | AR22: 17 | AS22: 74 | AT22: 35 | AU22: 17 | AV22: 14 | AW22: 36 | AX22: 92
A23: 10 | C23: 90 | D23: 45 | E23: 12 | F23: 53 | G23: 75 | H23: 83 | I23: 75 | J23: 61 | K23: 2 | L23: 10 | M23: 65 | N23: 26 | O23: 22 | P23: 89 | Q23: 83 | R23: 36 | S23: 12 | T23: 65 | U23: 43 | V23: 71 | W23: 68 | X23: 96 | Y23: 74 | Z23: 3 | AA23: 87 | AB23: 97 | AC23: 67 | AD23: 74 | AE23: 50 | AF23: 18 | AG23: 63 | AH23: 53 | AI23: 46 | AJ23: 53 | AK23: 38 | AL23: 89 | AM23: 79 | AN23: 48 | AO23: 64 | AP23: 39 | AQ23: 67 | AR23: 68 | AS23: 86 | AT23: 34 | AU23: 4 | AV23: 14 | AW23: 67 | AX23: 64
A25: Year
A26: 1 | C26: =ROUND(8760*C14/(SUM($C14:$AX14)),0) -> 59 | D26: =ROUND(8760*D14/(SUM($C14:$AX14)),0) -> 87 | E26: =ROUND(8760*E14/(SUM($C14:$AX14)),0) -> 111 | F26: =ROUND(8760*F14/(SUM($C14:$AX14)),0) -> 158 | G26: =ROUND(8760*G14/(SUM($C14:$AX14)),0) -> 4 | H26: =ROUND(8760*H14/(SUM($C14:$AX14)),0) -> 324 | I26: =ROUND(8760*I14/(SUM($C14:$AX14)),0) -> 328 | J26: =ROUND(8760*J14/(SUM($C14:$AX14)),0) -> 332 | ... AX26: =ROUND(8760*AX14/(SUM($C14:$AX14)),0) -> 221 | AY26: =SUM(C26:AX26) -> 8760
A27: 2 | C27: =ROUND(8760*C15/(SUM($C15:$AX15)),0) -> 251 | D27: =ROUND(8760*D15/(SUM($C15:$AX15)),0) -> 328 | E27: =ROUND(8760*E15/(SUM($C15:$AX15)),0) -> 80 | F27: =ROUND(8760*F15/(SUM($C15:$AX15)),0) -> 101 | G27: =ROUND(8760*G15/(SUM($C15:$AX15)),0) -> 84 | H27: =ROUND(8760*H15/(SUM($C15:$AX15)),0) -> 91 | I27: =ROUND(8760*I15/(SUM($C15:$AX15)),0) -> 154 | J27: =ROUND(8760*J15/(SUM($C15:$AX15)),0) -> 136 | ... AW27: =ROUND(8760*AW15/(SUM($C15:$AX15)),0) -> 133 | AX27: 339 | AY27: =SUM(C27:AX27) -> 8760
A28: 3 | C28: =ROUND(8760*C16/(SUM($C16:$AX16)),0) -> 366 | D28: =ROUND(8760*D16/(SUM($C16:$AX16)),0) -> 290 | E28: =ROUND(8760*E16/(SUM($C16:$AX16)),0) -> 362 | F28: =ROUND(8760*F16/(SUM($C16:$AX16)),0) -> 137 | G28: =ROUND(8760*G16/(SUM($C16:$AX16)),0) -> 125 | H28: =ROUND(8760*H16/(SUM($C16:$AX16)),0) -> 48 | I28: =ROUND(8760*I16/(SUM($C16:$AX16)),0) -> 258 | J28: =ROUND(8760*J16/(SUM($C16:$AX16)),0) -> 76 | ... AW28: =ROUND(8760*AW16/(SUM($C16:$AX16)),0) -> 225 | AX28: 7 | AY28: =SUM(C28:AX28) -> 8760
A29: 4 | C29: =ROUND(8760*C17/(SUM($C17:$AX17)),0) -> 82 | D29: =ROUND(8760*D17/(SUM($C17:$AX17)),0) -> 225 | E29: =ROUND(8760*E17/(SUM($C17:$AX17)),0) -> 108 | F29: =ROUND(8760*F17/(SUM($C17:$AX17)),0) -> 216 | G29: =ROUND(8760*G17/(SUM($C17:$AX17)),0) -> 163 | H29: =ROUND(8760*H17/(SUM($C17:$AX17)),0) -> 225 | I29: =ROUND(8760*I17/(SUM($C17:$AX17)),0) -> 320 | J29: =ROUND(8760*J17/(SUM($C17:$AX17)),0) -> 265 | ... AW29: =ROUND(8760*AW17/(SUM($C17:$AX17)),0) -> 16 | AX29: 289 | AY29: =SUM(C29:AX29) -> 8760
A30: 5 | C30: =ROUND(8760*C18/(SUM($C18:$AX18)),0) -> 18 | D30: =ROUND(8760*D18/(SUM($C18:$AX18)),0) -> 290 | E30: =ROUND(8760*E18/(SUM($C18:$AX18)),0) -> 147 | F30: =ROUND(8760*F18/(SUM($C18:$AX18)),0) -> 66 | G30: =ROUND(8760*G18/(SUM($C18:$AX18)),0) -> 346 | H30: =ROUND(8760*H18/(SUM($C18:$AX18)),0) -> 221 | I30: =ROUND(8760*I18/(SUM($C18:$AX18)),0) -> 48 | J30: =ROUND(8760*J18/(SUM($C18:$AX18)),0) -> 143 | ... AW30: =ROUND(8760*AW18/(SUM($C18:$AX18)),0) -> 221 | AX30: 149 | AY30: =SUM(C30:AX30) -> 8760
A31: 6 | C31: =ROUND(8760*C19/(SUM($C19:$AX19)),0) -> 249 | D31: =ROUND(8760*D19/(SUM($C19:$AX19)),0) -> 25 | E31: =ROUND(8760*E19/(SUM($C19:$AX19)),0) -> 287 | F31: =ROUND(8760*F19/(SUM($C19:$AX19)),0) -> 38 | G31: =ROUND(8760*G19/(SUM($C19:$AX19)),0) -> 28 | H31: =ROUND(8760*H19/(SUM($C19:$AX19)),0) -> 88 | I31: =ROUND(8760*I19/(SUM($C19:$AX19)),0) -> 148 | J31: =ROUND(8760*J19/(SUM($C19:$AX19)),0) -> 54 | ... AW31: =ROUND(8760*AW19/(SUM($C19:$AX19)),0) -> 287 | AX31: 265 | AY31: =SUM(C31:AX31) -> 8760
A32: 7 | C32: =ROUND(8760*C20/(SUM($C20:$AX20)),0) -> 184 | D32: =ROUND(8760*D20/(SUM($C20:$AX20)),0) -> 214 | E32: =ROUND(8760*E20/(SUM($C20:$AX20)),0) -> 293 | F32: =ROUND(8760*F20/(SUM($C20:$AX20)),0) -> 255 | G32: =ROUND(8760*G20/(SUM($C20:$AX20)),0) -> 375 | H32: =ROUND(8760*H20/(SUM($C20:$AX20)),0) -> 45 | I32: =ROUND(8760*I20/(SUM($C20:$AX20)),0) -> 240 | J32: =ROUND(8760*J20/(SUM($C20:$AX20)),0) -> 98 | ... AW32: =ROUND(8760*AW20/(SUM($C20:$AX20)),0) -> 26 | AX32: 189 | AY32: =SUM(C32:AX32) -> 8760
A33: 8 | C33: =ROUND(8760*C21/(SUM($C21:$AX21)),0) -> 174 | D33: =ROUND(8760*D21/(SUM($C21:$AX21)),0) -> 308 | E33: =ROUND(8760*E21/(SUM($C21:$AX21)),0) -> 267 | F33: =ROUND(8760*F21/(SUM($C21:$AX21)),0) -> 222 | G33: =ROUND(8760*G21/(SUM($C21:$AX21)),0) -> 85 | H33: =ROUND(8760*H21/(SUM($C21:$AX21)),0) -> 315 | I33: =ROUND(8760*I21/(SUM($C21:$AX21)),0) -> 85 | J33: =ROUND(8760*J21/(SUM($C21:$AX21)),0) -> 7 | ... AX33: =ROUND(8760*AX21/(SUM($C21:$AX21)),0) -> 56 | AY33: =SUM(C33:AX33) -> 8760
A34: 9 | C34: =ROUND(8760*C22/(SUM($C22:$AX22)),0) -> 38 | D34: =ROUND(8760*D22/(SUM($C22:$AX22)),0) -> 226 | E34: =ROUND(8760*E22/(SUM($C22:$AX22)),0) -> 111 | F34: =ROUND(8760*F22/(SUM($C22:$AX22)),0) -> 331 | G34: =ROUND(8760*G22/(SUM($C22:$AX22)),0) -> 17 | H34: =ROUND(8760*H22/(SUM($C22:$AX22)),0) -> 265 | I34: =ROUND(8760*I22/(SUM($C22:$AX22)),0) -> 90 | J34: =ROUND(8760*J22/(SUM($C22:$AX22)),0) -> 251 | ... AW34: =ROUND(8760*AW22/(SUM($C22:$AX22)),0) -> 125 | AX34: 321 | AY34: =SUM(C34:AX34) -> 8760
A35: 10 | C35: =ROUND(8760*C23/(SUM($C23:$AX23)),0) -> 300 | D35: =ROUND(8760*D23/(SUM($C23:$AX23)),0) -> 150 | E35: =ROUND(8760*E23/(SUM($C23:$AX23)),0) -> 40 | F35: =ROUND(8760*F23/(SUM($C23:$AX23)),0) -> 177 | G35: =ROUND(8760*G23/(SUM($C23:$AX23)),0) -> 250 | H35: =ROUND(8760*H23/(SUM($C23:$AX23)),0) -> 277 | I35: =ROUND(8760*I23/(SUM($C23:$AX23)),0) -> 250 | J35: =ROUND(8760*J23/(SUM($C23:$AX23)),0) -> 203 | ... AW35: =ROUND(8760*AW23/(SUM($C23:$AX23)),0) -> 223 | AX35: 211 | AY35: =SUM(C35:AX35) -> 8760
